Workbook

Sheet customers
A1: customer_id | B1: customer_name | C1: segment | D1: city | E1: country | F1: signup_date
A2: C0001 | B2: House and Sons | C2: Consumer | D2: South Todd | E2: Latvia | F2: 44807
A3: C0002 | B3: Barrera-Martin | C3: Consumer | D3: South Josephmouth | E3: Sweden | F3: 44935
A4: C0003 | B4: Bernard, Cowan and Peters | C4: Consumer | D4: Mooreport | E4: Estonia | F4: 44814
A5: C0004 | B5: Noah Brown | C5: SME | D5: Brianshire | E5: Poland | F5: 45279
A6: C0005 | B6: Moore, Yu and Miller | C6: SME | D6: North Brooke | E6: Sweden | F6: 45636
A7: C0006 | B7: Powell PLC | C7: SME | D7: New Brooke | E7: Latvia | F7: 45536
A8: C0007 | B8: Sandoval-Cunningham | C8: SME | D8: Sarahborough | E8: Netherlands | F8: 45626
A9: C0008 | B9: Allen-Foster | C9: Enterprise | D9: Stephenland | E9: Sweden | F9: 44439
A10: C0009 | B10: Murillo, Ferrell and Jones | C10: SME | D10: New Joseph | E10: Lithuania | F10: 46100
A11: C0010 | B11: Suarez LLC | C11: Consumer | D11: Ericside | E11: Estonia | F11: 45687
A12: C0011 | B12: Riggs, Roman and Rice | C12: Consumer | D12: Sarahville | E12: Netherlands | F12: 46110
A13: C0012 | B13: Brian Rodriguez | C13: Consumer | D13: West Juan | E13: Poland | F13: 44801
... A301: C0300 | B301: Johnny Brown | C301: SME | D301: Hillport | E301: Poland | F301: 45293

Sheet inventory_snapshots
A1: warehouse_id | B1: product_id | C1: snapshot_date | D1: stock_on_hand | E1: reorder_point
A2: WH01 | B2: P0104 | C2: 44957 | D2: 243 | E2: 172
A3: WH01 | B3: P0023 | C3: 44957 | D3: 961 | E3: 263
A4: WH01 | B4: P0033 | C4: 44957 | D4: 1140 | E4: 175
A5: WH01 | B5: P0013 | C5: 44957 | D5: 677 | E5: 59
A6: WH01 | B6: P0124 | C6: 44957 | D6: 840 | E6: 202
A7: WH01 | B7: P0175 | C7: 44957 | D7: 770 | E7: 236
A8: WH01 | B8: P0166 | C8: 44957 | D8: 1030 | E8: 130
A9: WH01 | B9: P0150 | C9: 44957 | D9: 783 | E9: 59
A10: WH01 | B10: P0171 | C10: 44957 | D10: 661 | E10: 201
A11: WH01 | B11: P0042 | C11: 44957 | D11: 1056 | E11: 63
A12: WH01 | B12: P0188 | C12: 44957 | D12: 228 | E12: 207
A13: WH01 | B13: P0140 | C13: 44957 | D13: 947 | E13: 296
... A19255: WH10 | B19255: P0066 | C19255: 45626 | D19255: 709 | E19255: 295

Sheet orders
A1: order_id | B1: customer_id | C1: order_date | D1: order_priority | E1: region
A2: ORD000104 | B2: C0275 | C2: 45387 | D2: Economy
A3: ORD000258 | B3: C0236 | C3: 45274 | D3: Standard
A4: ORD003300 | B4: C0068 | C4: 44991 | D4: Express
A5: ORD003057 | B5: C0146 | C5: 45321 | D5: Express
A6: ORD000697 | B6: C0104 | C6: 45237 | D6: Economy
A7: ORD004047 | B7: C0181 | C7: 45618 | D7: standard
A8: ORD005666 | B8: C0111 | C8: 45308 | D8: Economy
A9: ORD003739 | B9: C0091 | C9: 44983 | D9: Express
A10: ORD003779 | B10: C0239 | C10: 45003 | D10: Standard
A11: ORD002570 | B11: C0026 | C11: 45541 | D11: EXPRESS
A12: ORD003191 | B12: C0270 | C12: 45227 | D12: Express
A13: ORD002284 | B13: C0119 | C13: 45509 | D13: Standard
... A16: ORD000802 | B16: C0007 | C16: 45466 | D16: standard
A17: ORD005834 | C17: 45233 | D17: same day
A18: ORD000840 | B18: C0038 | C18: 45311 | D18: Express
A19: ORD000004 | B19: C0196 | C19: 45588 | D19: Same Day
A20: ORD005195 | B20: C0204 | C20: 45485 | D20: Same Day
A21: ORD000910 | B21: C0194 | C21: 45295 | D21: Standard
A22: ORD005909 | B22: C0135 | C22: 45244 | D22: Express
A23: ORD004418 | B23: C0137 | C23: 45094 | D23: Same Day
A24: ORD000563 | B24: C0203 | C24: 45035 | D24: STANDARD
A25: ORD000289 | B25: C0225 | C25: 45031 | D25: Standard
A26: ORD005641 | B26: C0174 | C26: 45346 | D26: Express
A27: ORD005650 | B27: C0268 | C27: 45041 | D27: Same Day
A28: ORD003814 | B28: C0223 | C28: 44984 | D28: Standard
A29: ORD003176 | B29: C0270 | C29: 45239 | D29: Standard
... A34: ORD001126 | B34: C0010 | C34: 45070 | D34: Express
A35: ORD002483 | C35: 45144 | D35: Standard
A36: ORD002449 | B36: C0149 | C36: 45460 | D36: Standard
A37: ORD004155 | B37: C0085 | C37: 45149 | D37: Economy
A38: ORD005273 | B38: C0226 | C38: 45215 | D38: Express
A39: ORD001381 | B39: C0096 | C39: 45304 | D39: Express
A40: ORD004066 | B40: C0267 | C40: 45390 | D40: Same Day
A41: ORD004746 | B41: C0233 | C41: 45024 | D41: Same Day
A42: ORD005990 | B42: C0261 | C42: 45231 | D42: Standard
A43: ORD001146 | B43: C0090 | C43: 45316 | D43: Standard
A44: ORD000214 | B44: C0079 | C44: 45372 | D44: Standard
A45: ORD005496 | B45: C0003 | C45: 45043 | D45: Express
A46: ORD001692 | B46: C0059 | C46: 45317 | D46: Standard
A47: ORD001428 | B47: C0136 | C47: 45611 | D47: standard
... A86: ORD004197 | B86: C0116 | C86: 45043 | D86: same day
A87: ORD005664 | C87: 45410 | D87: Standard
A88: ORD002963 | B88: C0064 | C88: 45021 | D88: Standard
A89: ORD002598 | B89: C0254 | C89: 45572 | D89: Express
A90: ORD000812 | B90: C0245 | C90: 45078 | D90: Standard
A91: ORD000845 | B91: C0043 | C91: 45360 | D91: EXPRESS
A92: ORD001701 | B92: C0344 | C92: 44981 | D92: Same Day
A93: ORD001854 | B93: C0095 | C93: 45506 | D93: Express
A94: ORD002661 | B94: C0209 | C94: 45247 | D94: Express
A95: ORD000829 | B95: C0067 | C95: 45249 | D95: Standard
A96: ORD002547 | B96: C0150 | C96: 45045 | D96: Express
A97: ORD004982 | B97: C0245 | C97: 45276 | D97: Standard
A98: ORD004716 | B98: C0010 | C98: 45462 | D98: Same Day
A99: ORD004563 | B99: C0204 | C99: 45112 | D99: Express
... A258: ORD005134 | B258: C0192 | C258: 45354 | D258: Express
A259: ORD004479 | C259: 45402 | D259: Standard
A260: ORD004587 | B260: C0072 | C260: 45187 | D260: Economy
A261: ORD004305 | B261: C0279 | C261: 45320 | D261: Economy
A262: ORD002710 | B262: C0171 | C262: 45071 | D262: Standard
A263: ORD002551 | B263: C0299 | C263: 45364 | D263: Same Day
A264: ORD003215 | B264: C0061 | C264: 45253 | D264: Same Day
A265: ORD005357 | B265: C0150 | C265: 45457 | D265: Standard
A266: ORD004969 | B266: C0137 | C266: 45457 | D266: EXPRESS
A267: ORD001855 | B267: C0191 | C267: 45559 | D267: Standard
A268: ORD003235 | B268: C0223 | C268: 45353 | D268: Express
A269: ORD003350 | B269: C0247 | C269: 45352 | D269: Economy
A270: ORD005406 | B270: C0228 | C270: 45137 | D270: SAME DAY
A271: ORD002525 | B271: C0277 | C271: 45448 | D271: Same Day
... A299: ORD003861 | B299: C0096 | C299: 45528 | D299: Express
A300: ORD004146 | C300: 45224 | D300: Same Day
A301: ORD005233 | B301: C0028 | C301: 45321 | D301: Same Day
A302: ORD002253 | B302: C0100 | C302: 45094 | D302: Same Day
A303: ORD001595 | B303: C0299 | C303: 45365 | D303: Same Day
A304: ORD002113 | B304: C0187 | C304: 45304 | D304: Same Day
A305: ORD005985 | B305: C0087 | C305: 45315 | D305: Same Day
A306: ORD004393 | B306: C0093 | C306: 45447 | D306: Same Day
A307: ORD000890 | B307: C0212 | C307: 45253 | D307: Same Day
A308: ORD001188 | B308: C0089 | C308: 45337 | D308: Same Day
A309: ORD004665 | B309: C0016 | C309: 45265 | D309: Standard
A310: ORD000276 | B310: C0203 | C310: 45595 | D310: Economy
A311: ORD003792 | B311: C0245 | C311: 45198 | D311: Economy
A312: ORD004254 | B312: C0131 | C312: 45430 | D312: Express
... A532: ORD005580 | B532: C0328 | C532: 45228 | D532: Economy
A533: ORD000119 | C533: 44947 | D533: Express
A534: ORD005886 | B534: C0078 | C534: 45169 | D534: Standard
A535: ORD000065 | B535: C0180 | C535: 45169 | D535: Same Day
A536: ORD003956 | B536: C0008 | C536: 45005 | D536: Same Day
A537: ORD003582 | B537: C0021 | C537: 45519 | D537: Express
A538: ORD000490 | B538: C0244 | C538: 45146 | D538: Economy
A539: ORD001064 | B539: C0125 | C539: 45410 | D539: Standard
A540: ORD003712 | B540: C0096 | C540: 45013 | D540: EXPRESS
A541: ORD003493 | B541: C0208 | C541: 45128 | D541: Express
A542: ORD001305 | B542: C0015 | C542: 45329 | D542: Same Day
A543: ORD001663 | B543: C0277 | C543: 45146 | D543: Express
A544: ORD001948 | B544: C0298 | C544: 45359 | D544: EXPRESS
A545: ORD002948 | B545: C0282 | C545: 44964 | D545: Express
... A1003: ORD004646 | B1003: C0137 | C1003: 45313 | D1003: ECONOMY
A1004: ORD002278 | C1004: 45517 | D1004: Express
A1005: ORD004544 | B1005: C0230 | C1005: 45322 | D1005: Standard
...

Sheet products
A1: product_id | B1: product_name | C1: category | D1: sub_category | E1: supplier_id | F1: unit_cost | G1: unit_price
A2: P0001 | B2: Winter Sports Image Max | C2: Outdoor & Sports | D2: Winter Sports | E2: SUP009 | F2: 221.4 | G2: 440.43
A3: P0002 | B3: Small Appliances I | C3: Home & Kitchen | D3: Small Appliances | E3: SUP019 | F3: 186.76 | G3: 349.21
A4: P0003 | B4: Winter Sports Pick Max | C4: Outdoor & Sports | D4: Winter Sports | E4: SUP017 | F4: 91.78 | G4: 219.99
A5: P0004 | B5: Camping Gear Management Max | C5: Outdoor & Sports | D5: Camping Gear | E5: SUP021 | F5: 189.43 | G5: 424.37
A6: P0005 | B6: Lighting Newspaper Basic | C6: Home & Kitchen | D6: Lighting | E6: SUP015 | F6: 149.91 | G6: 253.72
A7: P0006 | B7: Personal Care Enter Pro | C7: Health & Beauty | D7: Personal Care | E7: SUP022 | F7: 242.83 | G7: 543.91
A8: P0007 | B8: Speakers On Lite | C8: Electronics | D8: Speakers | E8: SUP004 | F8: 188.22 | G8: 401.64
A9: P0008 | B9: Filing Traditional | C9: Office Supplies | D9: Filing | E9: SUP024 | F9: 41.22 | G9: 51.68
A10: P0009 | B10: Desk Accessories Yes | C10: Office Supplies | D10: Desk Accessories | E10: SUP010 | F10: 127.91 | G10: 175.54 | I10: Row Labels | J10: Average of unit_cost | K10: Average of unit_price | L10: Margin
A11: P0010 | B11: Wellness Activity Max | C11: Health & Beauty | D11: Wellness | E11: SUP018 | F11: 51.33 | G11: 86.23 | I11: Electronics | J11: 126.386 | K11: 230.63886 | L11: =GETPIVOTDATA("Average of unit_price",$I$10,"category","Electronics")-GETPIVOTDATA("Average of unit_cost",$I$10,"category","Electronics") -> 104.25286
A12: P0011 | B12: Skincare Response Pro | C12: Health & Beauty | D12: Skincare | E12: SUP012 | F12: 150.54 | G12: 272.76 | I12: Health & Beauty | J12: 152.93889 | K12: 275.7025 | L12: =GETPIVOTDATA("Average of unit_price",$I$10,"category","Health & Beauty")-GETPIVOTDATA("Average of unit_cost",$I$10,"category","Health & Beauty") -> 122.76361
A13: P0012 | B13: Desk Accessories Set Pro | C13: Office Supplies | D13: Desk Accessories | E13: SUP003 | F13: 16.37 | G13: 36.99 | I13: Home & Kitchen | J13: 132.9625 | K13: 245.475 | L13: =GETPIVOTDATA("Average of unit_price",$I$10,"category","Home & Kitchen")-GETPIVOTDATA("Average of unit_cost",$I$10,"category","Home & Kitchen") -> 112.5125
A14: P0013 | B14: Camping Gear Building Max | C14: Outdoor & Sports | D14: Camping Gear | E14: SUP005 | F14: 244.54 | G14: 455.48 | I14: Office Supplies | J14: 131.58455 | K14: 242.94114 | L14: =GETPIVOTDATA("Average of unit_price",$I$10,"category","Office Supplies")-GETPIVOTDATA("Average of unit_cost",$I$10,"category","Office Supplies") -> 111.35659
A15: P0014 | B15: Cycling Rest Plus | C15: Outdoor & Sports | D15: Cycling | E15: SUP007 | F15: 67.73 | G15: 152.62 | I15: Outdoor & Sports | J15: 128.27623 | K15: 240.70868 | L15: =GETPIVOTDATA("Average of unit_price",$I$10,"category","Outdoor & Sports")-GETPIVOTDATA("Average of unit_cost",$I$10,"category","Outdoor & Sports") -> 112.43245
A16: P0015 | B16: Wellness Value Plus | C16: Health & Beauty | D16: Wellness | E16: SUP022 | F16: 173.09 | G16: 358.28 | I16: Grand Total | J16: 133.86235 | K16: 246.4991
A17: P0016 | B17: Filing Not Max | C17: Office Supplies | D17: Filing | E17: SUP008 | F17: 225.1 | G17: 398.25
A18: P0017 | B18: Smart Home Social Basic | C18: Electronics | D18: Smart Home | E18: SUP008 | F18: 7.22 | G18: 13.62
A19: P0018 | B19: Headphones Example Pro | C19: Electronics | D19: Headphones | E19: SUP002 | F19: 177.54 | G19: 233.95
A20: P0019 | B20: Paper Products Specific Plus | C20: Office Supplies | D20: Paper Products | E20: SUP007 | F20: 129.51 | G20: 203.36
A21: P0020 | B21: Skincare Put Basic | C21: Health & Beauty | D21: Skincare | E21: SUP016 | F21: 181.39 | G21: 410.8
A22: P0021 | B22: Lighting Grow Pro | C22: Home & Kitchen | D22: Lighting | E22: SUP022 | F22: 202.26 | G22: 297.11
A23: P0022 | B23: Fitness Brother | C23: Outdoor & Sports | D23: Fitness | E23: SUP002 | F23: 107.05 | G23: 191.31
A24: P0023 | B24: Headphones Finally Pro | C24: Electronics | D24: Headphones | E24: SUP008 | F24: 101.85 | G24: 167.05
A25: P0024 | B25: Small Appliances Learn Max | C25: Home & Kitchen | D25: Small Appliances | E25: SUP009 | F25: 135 | G25: 190.51
A26: P0025 | B26: Cycling Coach Basic | C26: Outdoor & Sports | D26: Cycling | E26: SUP004 | F26: 218.87 | G26: 292.56
A27: P0026 | B27: Speakers Long Max | C27: Electronics | D27: Speakers | E27: SUP006 | F27: 209.33 | G27: 494.93
A28: P0027 | B28: Winter Sports About Pro | C28: Outdoor & Sports | D28: Winter Sports | E28: SUP006 | F28: 121.38 | G28: 272.42
... A201: P0200 | B201: Wellness Administration Max | C201: Health & Beauty | D201: Wellness | E201: SUP014 | F201: 216.64 | G201: 377.95

Sheet Sup data
A1: shipment_id | B1: order_id | C1: carrier | D1: ship_date | E1: scheduled_delivery_date | F1: actual_delivery_date | G1: shipping_cost_eur | H1: delivery_status
A2: SHP0000001 | B2: ORD000104 | C2: UPS | D2: 45390 | E2: 45400 | F2: 45405 | G2: 57.47 | H2: Delivered
A3: SHP0000002 | B3: ORD000258 | C3: UPS | D3: 45275 | E3: 45282 | F3: 45289 | G3: 47.42 | H3: Delivered
A4: SHP0000003 | B4: ORD003300 | C4: DPD | D4: 44993 | E4: 44996 | F4: 45006 | G4: 48.51 | H4: delivered
A5: SHP0000004 | B5: ORD003057 | C5: DHL | D5: 45321 | E5: 45324 | F5: 45338 | G5: 53.15 | H5: DELIVERED
A6: SHP0000005 | B6: ORD000697 | C6: Matkahuolto | D6: 45239 | E6: 45246 | F6: 45246 | G6: 40.55 | H6: delivered
A7: SHP0000006 | B7: ORD004047 | C7: UPS | D7: 45620 | E7: 45623 | F7: 45625 | G7: 58.52 | H7: delivered
A8: SHP0000007 | B8: ORD005666 | C8: UPS | D8: 45310 | E8: 45315 | F8: 45323 | G8: 25.11 | H8: delivered
A9: SHP0000008 | B9: ORD003739 | C9: PostNord | D9: 44986 | E9: 44991 | F9: 44990 | G9: 61.23 | H9: delivered
A10: SHP0000009 | B10: ORD003779 | C10: PostNord | D10: 45006 | E10: 45013 | F10: 45013 | G10: 4.79 | H10: delivered
A11: SHP0000010 | B11: ORD002570 | C11: Budbee | D11: 45542 | E11: 45547 | F11: 45555 | G11: 57.47 | H11: delivered
A12: SHP0000011 | B12: ORD003191 | C12: Bring | D12: 45228 | E12: 45231 | F12: 45231 | G12: 27.82 | H12: delivered
A13: SHP0000012 | B13: ORD002284 | C13: UPS | D13: 45509 | E13: 45514 | F13: 45522 | G13: 16.29 | H13: DELIVERED
... A16: SHP0000015 | B16: ORD000802 | C16: DPD | D16: 45467 | E16: 45477 | F16: 45480 | G16: 45.08 | H16: delivered
A17: SHP0000016 | B17: ORD005834 | C17: DHL | D17: 45235 | E17: 45242 | G17: 21.44 | H17: in transit
A18: SHP0000017 | B18: ORD000840 | C18: DPD | D18: 45314 | E18: 45316 | F18: 45321 | G18: 49.57 | H18: delivered
A19: SHP0000018 | B19: ORD000004 | D19: 45588 | E19: 45595 | F19: 45594 | G19: 22.54 | H19: delivered
A20: SHP0000019 | B20: ORD005195 | C20: PostNord | D20: 45485 | E20: 45490 | G20: 46.55 | H20: in transit
A21: SHP0000020 | B21: ORD000910 | C21: PostNord | D21: 45298 | E21: 45301 | F21: 45302 | G21: 59.52 | H21: Delivered
A22: SHP0000021 | B22: ORD000910 | C22: Budbee | D22: 45296 | E22: 45306 | F22: 45308 | G22: 58.19 | H22: Delivered
A23: SHP0000022 | B23: ORD005909 | C23: Budbee | D23: 45246 | E23: 45249 | F23: 45259 | G23: 42.31 | H23: DELIVERED
A24: SHP0000023 | B24: ORD004418 | C24: PostNord | D24: 45097 | E24: 45102 | G24: 6.01 | H24: in transit
A25: SHP0000024 | B25: ORD000563 | C25: DB Schenker | D25: 45038 | E25: 45041 | F25: 45042 | G25: 10.22 | H25: DELIVERED
A26: SHP0000025 | B26: ORD000289 | C26: PostNord | D26: 45033 | E26: 45043 | G26: 15.78 | H26: IN TRANSIT
A27: SHP0000026 | B27: ORD005641 | C27: Bring | D27: 45348 | E27: 45355 | F27: 45356 | G27: 10.75 | H27: delivered
A28: SHP0000027 | B28: ORD005650 | D28: 45042 | E28: 45052 | F28: 45052 | G28: 51.79 | H28: DELIVERED
A29: SHP0000028 | B29: ORD005650 | C29: Bring | D29: 45043 | E29: 45046 | F29: 45049 | G29: 58.78 | H29: Delivered
A30: SHP0000029 | B30: ORD003814 | C30: Budbee | D30: 44987 | E30: 44994 | G30: 34.6 | H30: Cancelled
A31: SHP0000030 | B31: ORD003176 | C31: Matkahuolto | D31: 45239 | E31: 45246 | F31: 45249 | G31: 57.71 | H31: Delivered
A32: SHP0000031 | B32: ORD002824 | C32: Budbee | D32: 44982 | E32: 44989 | F32: 44991 | G32: 28.78 | H32: Delivered
A33: SHP0000032 | B33: ORD002314 | C33: Bring | D33: 45204 | E33: 45206 | F33: 45216 | G33: 26.25 | H33: delivered
A34: SHP0000033 | B34: ORD003871 | C34: UPS | D34: 44963 | E34: 44970 | F34: 44978 | G34: 6.72 | H34: delivered
A35: SHP0000034 | B35: ORD000815 | C35: UPS | D35: 45162 | E35: 45172 | F35: 45172 | G35: 26.4 | H35: delivered
A36: SHP0000035 | B36: ORD001126 | C36: Budbee | D36: 45070 | E36: 45072 | G36: 17.93 | H36: Cancelled
A37: SHP0000036 | B37: ORD002483 | C37: UPS | D37: 45144 | E37: 45151 | F37: 45154 | G37: 41.16 | H37: Delivered
A38: SHP0000037 | B38: ORD002449 | C38: UPS | D38: 45460 | E38: 45462 | G38: 35.3 | H38: CANCELLED
A39: SHP0000038 | B39: ORD004155 | C39: UPS | D39: 45150 | E39: 45155 | F39: 45155 | G39: 4.72 | H39: DELIVERED
A40: SHP0000039 | B40: ORD005273 | C40: DHL | D40: 45215 | E40: 45218 | F40: 45218 | G40: 18.31 | H40: DELIVERED
A41: SHP0000040 | B41: ORD001381 | C41: UPS | D41: 45307 | E41: 45310 | F41: 45324 | H41: delivered
A42: SHP0000041 | B42: ORD004066 | C42: PostNord | D42: 45391 | E42: 45393 | G42: 55.06 | H42: In Transit
A43: SHP0000042 | B43: ORD004746 | C43: DPD | D43: 45026 | E43: 45029 | G43: 11.37 | H43: cancelled
A44: SHP0000043 | B44: ORD005990 | C44: UPS | D44: 45233 | E44: 45240 | F44: 45241 | G44: 30.3 | H44: delivered
A45: SHP0000044 | B45: ORD001146 | C45: DB Schenker | D45: 45316 | E45: 45319 | F45: 45331 | G45: 21.18 | H45: DELIVERED
A46: SHP0000045 | B46: ORD000214 | C46: Budbee | D46: 45374 | E46: 45377 | F46: 45380 | G46: 62.69 | H46: Delivered
A47: SHP0000046 | B47: ORD005496 | C47: DB Schenker | D47: 45043 | E47: 45050 | F47: 45052 | G47: 16.23 | H47: Delivered
A48: SHP0000047 | B48: ORD001692 | C48: PostNord | D48: 45318 | E48: 45321 | F48: 45320 | G48: 59.16 | H48: DELIVERED
A49: SHP0000048 | B49: ORD001428 | C49: Bring | D49: 45611 | E49: 45618 | F49: 45620 | G49: 49.33 | H49: Delivered
A50: SHP0000049 | B50: ORD001428 | C50: PostNord | D50: 45614 | E50: 45624 | F50: 45638 | G50: 61.49 | H50: Delivered
A51: SHP0000050 | B51: ORD002211 | C51: Bring | D51: 45451 | E51: 45458 | F51: 45463 | H51: Delivered
A52: SHP0000051 | B52: ORD001117 | C52: Bring | D52: 45381 | E52: 45384 | F52: 45390 | G52: 20.07 | H52: DELIVERED
A53: SHP0000052 | B53: ORD004081 | C53: Matkahuolto | D53: 45452 | E53: 45459 | G53: 6.16 | H53: IN TRANSIT
A54: SHP0000053 | B54: ORD000585 | C54: PostNord | D54: 44990 | E54: 44995 | F54: 45008 | G54: 48.51 | H54: Delivered
A55: SHP0000054 | B55: ORD002415 | C55: Budbee | D55: 45115 | E55: 45117 | F55: 45117 | G55: 22.94 | H55: DELIVERED
A56: SHP0000055 | B56: ORD004806 | C56: DPD | D56: 45411 | E56: 45413 | F56: 45418 | G56: 31.85 | H56: DELIVERED
A57: SHP0000056 | B57: ORD003945 | C57: DHL | D57: 45082 | E57: 45085 | F57: 45099 | G57: 10.65 | H57: Delivered
A58: SHP0000057 | B58: ORD005318 | C58: UPS | D58: 45241 | E58: 45251 | F58: 45259 | G58: 34.4 | H58: DELIVERED
A59: SHP0000058 | B59: ORD002193 | C59: DPD | D59: 45408 | E59: 45415 | H59: IN TRANSIT
A60: SHP0000059 | B60: ORD002193 | C60: DPD | D60: 45408 | E60: 45411 | G60: 13.85 | H60: IN TRANSIT
A61: SHP0000060 | B61: ORD000028 | C61: Bring | D61: 45598 | E61: 45603 | F61: 45608 | G61: 21.17 | H61: DELIVERED
A62: SHP0000061 | B62: ORD001776 | C62: DHL | D62: 45382 | E62: 45385 | F62: 45387 | G62: 64.47 | H62: Delivered
A63: SHP0000062 | B63: ORD000266 | C63: DHL | D63: 45460 | E63: 45470 | F63: 45473 | G63: 27.65 | H63: DELIVERED
A64: SHP0000063 | B64: ORD001576 | C64: DHL | D64: 45555 | E64: 45562 | F64: 45562 | G64: 38.82 | H64: DELIVERED
A65: SHP0000064 | B65: ORD002213 | C65: DPD | D65: 45245 | E65: 45252 | F65: 45251 | G65: 24.15 | H65: Delivered
A66: SHP0000065 | B66: ORD002207 | C66: Budbee | D66: 45560 | E66: 45562 | G66: 34.93 | H66: Cancelled
A67: SHP0000066 | B67: ORD001827 | C67: DB Schenker | D67: 45306 | E67: 45313 | F67: 45315 | G67: 26.44 | H67: Delivered
A68: SHP0000067 | B68: ORD000089 | C68: Matkahuolto | D68: 45393 | E68: 45395 | F68: 45395 | G68: 8.96 | H68: DELIVERED
A69: SHP0000068 | B69: ORD001449 | C69: DB Schenker | D69: 44971 | E69: 44974 | F69: 44975 | G69: 19.36 | H69: delivered
A70: SHP0000069 | B70: ORD001449 | C70: Matkahuolto | D70: 44970 | E70: 44980 | F70: 44980 | G70: 48.72 | H70: delivered
A71: SHP0000070 | B71: ORD001238 | C71: DHL | D71: 44988 | E71: 44995 | G71: 47.87 | H71: cancelled
A72: SHP0000071 | B72: ORD001750 | C72: DB Schenker | D72: 45338 | E72: 45340 | G72: 14.85 | H72: in transit
A73: SHP0000072 | B73: ORD004436 | C73: DPD | D73: 45560 | E73: 45563 | F73: 45562 | G73: 64.22 | H73: DELIVERED
A74: SHP0000073 | B74: ORD003169 | C74: PostNord | D74: 45169 | E74: 45179 | G74: 8.18 | H74: In Transit
A75: SHP0000074 | B75: ORD001009 | C75: DPD | D75: 45514 | E75: 45521 | F75: 45521 | G75: 33.22 | H75: DELIVERED
A76: SHP0000075 | B76: ORD000339 | C76: DPD | D76: 45580 | E76: 45582 | F76: 45583 | G76: 57.35 | H76: DELIVERED
A77: SHP0000076 | B77: ORD000339 | C77: Bring | D77: 45582 | E77: 45585 | F77: 45593 | G77: 47.22 | H77: DELIVERED
A78: SHP0000077 | B78: ORD005170 | C78: DB Schenker | D78: 45621 | E78: 45624 | F78: 45629 | G78: 60.05 | H78: DELIVERED
A79: SHP0000078 | B79: ORD000647 | C79: DB Schenker | D79: 45198 | E79: 45203 | F79: 45213 | G79: 20.67 | H79: Delivered
A80: SHP0000079 | B80: ORD005417 | C80: DB Schenker | D80: 45287 | E80: 45289 | F80: 45288 | G80: 36.84 | H80: DELIVERED
A81: SHP0000080 | B81: ORD002669 | C81: Bring | D81: 45575 | E81: 45585 | F81: 45585 | G81: 11.39 | H81: DELIVERED
A82: SHP0000081 | B82: ORD000745 | C82: PostNord | D82: 45597 | E82: 45602 | F82: 45604 | G82: 25.94 | H82: DELIVERED
A83: SHP0000082 | B83: ORD004501 | C83: DHL | D83: 45410 | E83: 45420 | F83: 45425 | G83: 36.58 | H83: Delivered
A84: SHP0000083 | B84: ORD002888 | C84: DB Schenker | D84: 45121 | E84: 45126 | F84: 45129 | G84: 26.27 | H84: delivered
A85: SHP0000084 | B85: ORD002888 | C85: DHL | D85: 45120 | E85: 45125 | F85: 45130 | G85: 28.63 | H85: Delivered
A86: SHP0000085 | B86: ORD002389 | C86: PostNord | D86: 45331 | E86: 45336 | F86: 45336 | G86: 40.18 | H86: DELIVERED
... A98: SHP0000097 | B98: ORD000845 | C98: DHL | D98: 45361 | E98: 45368 | F98: 45371 | G98: 26.74 | H98: delivered
A99: SHP0000098 | B99: ORD001701 | C99: Budbee | D99: 44983 | E99: 44985 | G99: 62.9 | H99: in transit
A100: SHP0000099 | B100: ORD001854 | C100: DB Schenker | D100: 45506 | E100: 45513 | G100: 43.21 | H100: cancelled
A101: SHP0000100 | B101: ORD002661 | C101: DHL | D101: 45250 | E101: 45255 | F101: 45260 | G101: 25.92 | H101: Delivered
A102: SHP0000101 | B102: ORD000829 | C102: Matkahuolto | D102: 45250 | E102: 45252 | F102: 45254 | G102: 7.59 | H102: DELIVERED
A103: SHP0000102 | B103: ORD002547 | C103: DB Schenker | D103: 45045 | E103: 45048 | G103: 23.42 | H103: Cancelled
A104: SHP0000103 | B104: ORD002547 | C104: Budbee | D104: 45046 | E104: 45049 | G104: 33.15 | H104: Cancelled
A105: SHP0000104 | B105: ORD004982 | C105: DB Schenker | D105: 45279 | E105: 45282 | F105: 45295 | G105: 55.86 | H105: Delivered
A106: SHP0000105 | B106: ORD004716 | C106: DHL | D106: 45462 | E106: 45467 | F106: 45467 | G106: 37.9 | H106: delivered
A107: SHP0000106 | B107: ORD004563 | C107: UPS | D107: 45115 | E107: 45117 | F107: 45117 | G107: 18.31 | H107: delivered
A108: SHP0000107 | B108: ORD000202 | C108: DHL | D108: 45503 | E108: 45513 | F108: 45523 | G108: 6.35 | H108: delivered
A109: SHP0000108 | B109: ORD000739 | C109: PostNord | D109: 45457 | E109: 45460 | G109: 13.75 | H109: In Transit
A110: SHP0000109 | B110: ORD002725 | C110: DB Schenker | D110: 45617 | E110: 45622 | F110: 45622 | G110: 64.11 | H110: delivered
A111: SHP0000110 | B111: ORD004063 | C111: UPS | D111: 45503 | E111: 45505 | F111: 45505 | G111: 25.94 | H111: DELIVERED
A112: SHP0000111 | B112: ORD000954 | C112: DB Schenker | D112: 45367 | E112: 45369 | F112: 45368 | G112: 22.89 | H112: DELIVERED
A113: SHP0000112 | B113: ORD001157 | C113: DB Schenker | D113: 45410 | E113: 45415 | F113: 45415 | G113: 6.94 | H113: DELIVERED
...

Sheet suppliers
A1: supplier_id | B1: supplier_name | C1: country | D1: avg_lead_time_days | E1: reliability_rating | F1: contract_start
A2: SUP001 | B2: Rodriguez, Figueroa and Sanchez | C2: Germany | D2: 6 | E2: 4.4 | F2: 44312
A3: SUP002 | B3: Rhodes PLC | C3: Vietnam | D3: 19 | E3: 3.1 | F3: 44216
A4: SUP003 | B4: Johnson-Davis | C4: Germany | D4: 39 | E4: 3 | F4: 44482
A5: SUP004 | B5: Johnson, Gonzalez and Santos | C5: Sweden | D5: 7 | E5: 2.9 | F5: 45053
A6: SUP005 | B6: Cole LLC | C6: Vietnam | D6: 19 | E6: 3.9 | F6: 45536
A7: SUP006 | B7: Blake and Sons | C7: China | D7: 40 | E7: 3.2 | F7: 45332
A8: SUP007 | B8: Ramirez-Lewis | C8: South Korea | D8: 31 | E8: 3.3 | F8: 45452
A9: SUP008 | B9: Davis Inc | C9: Netherlands | D9: 22 | E9: 4.6 | F9: 44713
A10: SUP009 | B10: Munoz-Roman | C10: China | D10: 15 | E10: 4.3 | F10: 45390
A11: SUP010 | B11: Martinez, Nielsen and Miller | C11: Finland | D11: 22 | E11: 3.1 | F11: 44593
A12: SUP011 | B12: Montgomery, Hensley and Ray | C12: Finland | D12: 11 | E12: 3 | F12: 45344
A13: SUP012 | B13: Stanley LLC | C13: Germany | D13: 27 | E13: 4.7 | F13: 45857
... A26: SUP025 | B26: Conner Group | C26: South Korea | D26: 19 | E26: 4.3 | F26: 45147

Sheet warehouses
A1: warehouse_id | B1: warehouse_name | C1: city | D1: country | E1: capacity_units
A2: WH01 | B2: Helsinki DC | C2: Helsinki | D2: Finland | E2: 27331
A3: WH02 | B3: Jyvaskyla Regional Hub | C3: Jyvaskyla | D3: Finland | E3: 50021
A4: WH03 | B4: Stockholm DC | C4: Stockholm | D4: Sweden | E4: 24207
A5: WH04 | B5: Oslo DC | C5: Oslo | D5: Norway | E5: 61347
A6: WH05 | B6: Copenhagen DC | C6: Copenhagen | D6: Denmark | E6: 72581
A7: WH06 | B7: Tallinn Hub | C7: Tallinn | D7: Estonia | E7: 55093
A8: WH07 | B8: Riga Hub | C8: Riga | D8: Latvia | E8: 28675
A9: WH08 | B9: Gdansk DC | C9: Gdansk | D9: Poland | E9: 47653
A10: WH09 | B10: Berlin DC | C10: Berlin | D10: Germany | E10: 61245
A11: WH10 | B11: Amsterdam DC | C11: Amsterdam | D11: Netherlands | E11: 47869

Sheet order_items
A1: order_item_id | B1: order_id | C1: Date | D1: Month | E1: Category | F1: product_id | G1: warehouse_id | H1: quantity | I1: unit_price | J1: discount
A2: OI0000001 | B2: ORD000104 | C2: =_xlfn.XLOOKUP(order_items[[#This Row],[order_id]],orders!A:A,orders!C:C) -> 45387 | D2: =YEAR(order_items[[#This Row],[Date]])&"-"&TEXT(MONTH(order_items[[#This Row],[Date]]),"00") -> 2024-04 | E2: =_xlfn.XLOOKUP(order_items[[#This Row],[product_id]],products!A:A,products!C:C) -> Outdoor & Sports | F2: P0088 | G2: WH06 | H2: 9 | I2: 374.4 | J2: 0.05
A3: OI0000002 | B3: ORD000258 | C3: =_xlfn.XLOOKUP(order_items[[#This Row],[order_id]],orders!A:A,orders!C:C) -> 45274 | D3: =YEAR(order_items[[#This Row],[Date]])&"-"&TEXT(MONTH(order_items[[#This Row],[Date]]),"00") -> 2023-12 | E3: =_xlfn.XLOOKUP(order_items[[#This Row],[product_id]],products!A:A,products!C:C) -> Outdoor & Sports | F3: P0059 | G3: WH06 | H3: 4 | I3: 285.12 | J3: 0.15
A4: OI0000003 | B4: ORD000258 | C4: =_xlfn.XLOOKUP(order_items[[#This Row],[order_id]],orders!A:A,orders!C:C) -> 45274 | D4: =YEAR(order_items[[#This Row],[Date]])&"-"&TEXT(MONTH(order_items[[#This Row],[Date]]),"00") -> 2023-12 | E4: =_xlfn.XLOOKUP(order_items[[#This Row],[product_id]],products!A:A,products!C:C) -> Outdoor & Sports | F4: P0004 | G4: WH08 | H4: 17 | I4: 424.37 | J4: 0
A5: OI0000004 | B5: ORD000258 | C5: =_xlfn.XLOOKUP(order_items[[#This Row],[order_id]],orders!A:A,orders!C:C) -> 45274 | D5: =YEAR(order_items[[#This Row],[Date]])&"-"&TEXT(MONTH(order_items[[#This Row],[Date]]),"00") -> 2023-12 | E5: =_xlfn.XLOOKUP(order_items[[#This Row],[product_id]],products!A:A,products!C:C) -> Health & Beauty | F5: P0189 | G5: WH03 | H5: 6 | I5: 322.11 | J5: 0
A6: OI0000005 | B6: ORD003300 | C6: =_xlfn.XLOOKUP(order_items[[#This Row],[order_id]],orders!A:A,orders!C:C) -> 44991 | D6: =YEAR(order_items[[#This Row],[Date]])&"-"&TEXT(MONTH(order_items[[#This Row],[Date]]),"00") -> 2023-03 | E6: =_xlfn.XLOOKUP(order_items[[#This Row],[product_id]],products!A:A,products!C:C) -> Electronics | F6: P0187 | G6: WH02 | H6: 5 | I6: 312.08 | J6: 0
A7: OI0000006 | B7: ORD003300 | C7: =_xlfn.XLOOKUP(order_items[[#This Row],[order_id]],orders!A:A,orders!C:C) -> 44991 | D7: =YEAR(order_items[[#This Row],[Date]])&"-"&TEXT(MONTH(order_items[[#This Row],[Date]]),"00") -> 2023-03 | E7: =_xlfn.XLOOKUP(order_items[[#This Row],[product_id]],products!A:A,products!C:C) -> Home & Kitchen | F7: P0171 | G7: WH08 | H7: 24 | I7: 450.56 | J7: 0
A8: OI0000007 | B8: ORD003057 | C8: =_xlfn.XLOOKUP(order_items[[#This Row],[order_id]],orders!A:A,orders!C:C) -> 45321 | D8: =YEAR(order_items[[#This Row],[Date]])&"-"&TEXT(MONTH(order_items[[#This Row],[Date]]),"00") -> 2024-01 | E8: =_xlfn.XLOOKUP(order_items[[#This Row],[product_id]],products!A:A,products!C:C) -> Home & Kitchen | F8: P0150 | G8: WH05 | H8: 15 | I8: 218.39 | J8: 0
A9: OI0000008 | B9: ORD003057 | C9: =_xlfn.XLOOKUP(order_items[[#This Row],[order_id]],orders!A:A,orders!C:C) -> 45321 | D9: =YEAR(order_items[[#This Row],[Date]])&"-"&TEXT(MONTH(order_items[[#This Row],[Date]]),"00") -> 2024-01 | E9: =_xlfn.XLOOKUP(order_items[[#This Row],[product_id]],products!A:A,products!C:C) -> Health & Beauty | F9: P0113 | G9: WH07 | H9: 14 | I9: 98.57 | J9: 0
A10: OI0000009 | B10: ORD003057 | C10: =_xlfn.XLOOKUP(order_items[[#This Row],[order_id]],orders!A:A,orders!C:C) -> 45321 | D10: =YEAR(order_items[[#This Row],[Date]])&"-"&TEXT(MONTH(order_items[[#This Row],[Date]]),"00") -> 2024-01 | E10: =_xlfn.XLOOKUP(order_items[[#This Row],[product_id]],products!A:A,products!C:C) -> Health & Beauty | F10: P0034 | G10: WH01 | H10: 24 | I10: 306.07 | J10: 0.05
A11: OI0000010 | B11: ORD000697 | C11: =_xlfn.XLOOKUP(order_items[[#This Row],[order_id]],orders!A:A,orders!C:C) -> 45237 | D11: =YEAR(order_items[[#This Row],[Date]])&"-"&TEXT(MONTH(order_items[[#This Row],[Date]]),"00") -> 2023-11 | E11: =_xlfn.XLOOKUP(order_items[[#This Row],[product_id]],products!A:A,products!C:C) -> Electronics | F11: P0138 | G11: WH10 | H11: 9 | I11: 152.98 | J11: 0.1
A12: OI0000011 | B12: ORD000697 | C12: =_xlfn.XLOOKUP(order_items[[#This Row],[order_id]],orders!A:A,orders!C:C) -> 45237 | D12: =YEAR(order_items[[#This Row],[Date]])&"-"&TEXT(MONTH(order_items[[#This Row],[Date]]),"00") -> 2023-11 | E12: =_xlfn.XLOOKUP(order_items[[#This Row],[product_id]],products!A:A,products!C:C) -> Home & Kitchen | F12: P0060 | G12: WH07 | H12: 17 | I12: 255.1 | J12: 0.05
A13: OI0000012 | B13: ORD004047 | C13: =_xlfn.XLOOKUP(order_items[[#This Row],[order_id]],orders!A:A,orders!C:C) -> 45618 | D13: =YEAR(order_items[[#This Row],[Date]])&"-"&TEXT(MONTH(order_items[[#This Row],[Date]]),"00") -> 2024-11 | E13: =_xlfn.XLOOKUP(order_items[[#This Row],[product_id]],products!A:A,products!C:C) -> Electronics | F13: P0158 | G13: WH01 | H13: 3 | I13: 519.7 | J13: 0.05
... A16: OI0000015 | B16: ORD005666 | C16: =_xlfn.XLOOKUP(order_items[[#This Row],[order_id]],orders!A:A,orders!C:C) -> 45308 | D16: =YEAR(order_items[[#This Row],[Date]])&"-"&TEXT(MONTH(order_items[[#This Row],[Date]]),"00") -> 2024-01 | E16: =_xlfn.XLOOKUP(order_items[[#This Row],[product_id]],products!A:A,products!C:C) -> Health & Beauty | F16: P0030 | G16: WH10 | H16: 6 | I16: 246.7 | J16: 0
A17: OI0000016 | B17: ORD005666 | C17: =_xlfn.XLOOKUP(order_items[[#This Row],[order_id]],orders!A:A,orders!C:C) -> 45308 | D17: =YEAR(order_items[[#This Row],[Date]])&"-"&TEXT(MONTH(order_items[[#This Row],[Date]]),"00") -> 2024-01 | E17: =_xlfn.XLOOKUP(order_items[[#This Row],[product_id]],products!A:A,products!C:C) -> Electronics | F17: P0133 | G17: WH03 | H17: 18 | I17: 237.27 | J17: 0.15 | L17: Sum of quantity | M17: Column Labels
A18: OI0000017 | B18: ORD003739 | C18: =_xlfn.XLOOKUP(order_items[[#This Row],[order_id]],orders!A:A,orders!C:C) -> 44983 | D18: =YEAR(order_items[[#This Row],[Date]])&"-"&TEXT(MONTH(order_items[[#This Row],[Date]]),"00") -> 2023-02 | E18: =_xlfn.XLOOKUP(order_items[[#This Row],[product_id]],products!A:A,products!C:C) -> Office Supplies | F18: P0188 | G18: WH03 | H18: 17 | I18: 532.79 | J18: 0 | L18: Row Labels | M18: Electronics | N18: Health & Beauty | O18: Home & Kitchen | P18: Office Supplies | Q18: Outdoor & Sports | R18: Grand Total
A19: OI0000018 | B19: ORD003779 | C19: =_xlfn.XLOOKUP(order_items[[#This Row],[order_id]],orders!A:A,orders!C:C) -> 45003 | D19: =YEAR(order_items[[#This Row],[Date]])&"-"&TEXT(MONTH(order_items[[#This Row],[Date]]),"00") -> 2023-03 | E19: =_xlfn.XLOOKUP(order_items[[#This Row],[product_id]],products!A:A,products!C:C) -> Health & Beauty | F19: P0067 | G19: WH05 | H19: 10 | I19: 59 | J19: 0 | L19: 2023-01 | M19: 893 | N19: 1114 | O19: 945 | P19: 1536 | Q19: 1357 | R19: 5845
A20: OI0000019 | B20: ORD003779 | C20: =_xlfn.XLOOKUP(order_items[[#This Row],[order_id]],orders!A:A,orders!C:C) -> 45003 | D20: =YEAR(order_items[[#This Row],[Date]])&"-"&TEXT(MONTH(order_items[[#This Row],[Date]]),"00") -> 2023-03 | E20: =_xlfn.XLOOKUP(order_items[[#This Row],[product_id]],products!A:A,products!C:C) -> Office Supplies | F20: P0167 | G20: WH08 | H20: 25 | I20: 490.76 | J20: 0.05 | L20: 2023-02 | M20: 883 | N20: 1255 | O20: 1183 | P20: 1339 | Q20: 1710 | R20: 6370
A21: OI0000020 | B21: ORD002570 | C21: =_xlfn.XLOOKUP(order_items[[#This Row],[order_id]],orders!A:A,orders!C:C) -> 45541 | D21: =YEAR(order_items[[#This Row],[Date]])&"-"&TEXT(MONTH(order_items[[#This Row],[Date]]),"00") -> 2024-09 | E21: =_xlfn.XLOOKUP(order_items[[#This Row],[product_id]],products!A:A,products!C:C) -> Office Supplies | F21: P0045 | G21: WH02 | H21: 10 | I21: 350.18 | J21: 0.15 | L21: 2023-03 | M21: 1120 | N21: 1295 | O21: 1085 | P21: 1430 | Q21: 1578 | R21: 6508
A22: OI0000021 | B22: ORD002570 | C22: =_xlfn.XLOOKUP(order_items[[#This Row],[order_id]],orders!A:A,orders!C:C) -> 45541 | D22: =YEAR(order_items[[#This Row],[Date]])&"-"&TEXT(MONTH(order_items[[#This Row],[Date]]),"00") -> 2024-09 | E22: =_xlfn.XLOOKUP(order_items[[#This Row],[product_id]],products!A:A,products!C:C) -> Outdoor & Sports | F22: P0075 | G22: WH08 | H22: 15 | I22: 101.7 | J22: 0.05 | L22: 2023-04 | M22: 1077 | N22: 1114 | O22: 997 | P22: 1486 | Q22: 1679 | R22: 6353
A23: OI0000022 | B23: ORD003191 | C23: =_xlfn.XLOOKUP(order_items[[#This Row],[order_id]],orders!A:A,orders!C:C) -> 45227 | D23: =YEAR(order_items[[#This Row],[Date]])&"-"&TEXT(MONTH(order_items[[#This Row],[Date]]),"00") -> 2023-10 | E23: =_xlfn.XLOOKUP(order_items[[#This Row],[product_id]],products!A:A,products!C:C) -> Health & Beauty | F23: P0148 | G23: WH04 | H23: 9 | I23: 175.38 | J23: 0 | L23: 2023-05 | M23: 1105 | N23: 1391 | O23: 866 | P23: 1261 | Q23: 1672 | R23: 6295
A24: OI0000023 | B24: ORD003191 | C24: =_xlfn.XLOOKUP(order_items[[#This Row],[order_id]],orders!A:A,orders!C:C) -> 45227 | D24: =YEAR(order_items[[#This Row],[Date]])&"-"&TEXT(MONTH(order_items[[#This Row],[Date]]),"00") -> 2023-10 | E24: =_xlfn.XLOOKUP(order_items[[#This Row],[product_id]],products!A:A,products!C:C) -> Office Supplies | F24: P0191 | G24: WH07 | H24: 16 | I24: 65.73 | J24: 0.1 | L24: 2023-06 | M24: 1172 | N24: 804 | O24: 623 | P24: 1060 | Q24: 1372 | R24: 5031
A25: OI0000024 | B25: ORD002284 | C25: =_xlfn.XLOOKUP(order_items[[#This Row],[order_id]],orders!A:A,orders!C:C) -> 45509 | D25: =YEAR(order_items[[#This Row],[Date]])&"-"&TEXT(MONTH(order_items[[#This Row],[Date]]),"00") -> 2024-08 | E25: =_xlfn.XLOOKUP(order_items[[#This Row],[product_id]],products!A:A,products!C:C) -> Office Supplies | F25: P0144 | G25: WH04 | H25: 5 | I25: 189.58 | J25: 0.15 | L25: 2023-07 | M25: 1044 | N25: 876 | O25: 1014 | P25: 1301 | Q25: 1402 | R25: 5637
A26: OI0000025 | B26: ORD004946 | C26: =_xlfn.XLOOKUP(order_items[[#This Row],[order_id]],orders!A:A,orders!C:C) -> 45341 | D26: =YEAR(order_items[[#This Row],[Date]])&"-"&TEXT(MONTH(order_items[[#This Row],[Date]]),"00") -> 2024-02 | E26: =_xlfn.XLOOKUP(order_items[[#This Row],[product_id]],products!A:A,products!C:C) -> Health & Beauty | F26: P0140 | G26: WH02 | H26: 25 | I26: 406.99 | J26: 0 | L26: 2023-08 | M26: 1065 | N26: 1214 | O26: 964 | P26: 1101 | Q26: 1727 | R26: 6071
A27: OI0000026 | B27: ORD004946 | C27: =_xlfn.XLOOKUP(order_items[[#This Row],[order_id]],orders!A:A,orders!C:C) -> 45341 | D27: =YEAR(order_items[[#This Row],[Date]])&"-"&TEXT(MONTH(order_items[[#This Row],[Date]]),"00") -> 2024-02 | E27: =_xlfn.XLOOKUP(order_items[[#This Row],[product_id]],products!A:A,products!C:C) -> Home & Kitchen | F27: P0127 | G27: WH09 | H27: 6 | I27: 45.95 | J27: 0 | L27: 2023-09 | M27: 984 | N27: 1050 | O27: 1056 | P27: 1297 | Q27: 1499 | R27: 5886
A28: OI0000027 | B28: ORD004946 | C28: =_xlfn.XLOOKUP(order_items[[#This Row],[order_id]],orders!A:A,orders!C:C) -> 45341 | D28: =YEAR(order_items[[#This Row],[Date]])&"-"&TEXT(MONTH(order_items[[#This Row],[Date]]),"00") -> 2024-02 | E28: =_xlfn.XLOOKUP(order_items[[#This Row],[product_id]],products!A:A,products!C:C) -> Electronics | F28: P0133 | G28: WH07 | H28: 4 | I28: 237.27 | J28: 0.05 | L28: 2023-10 | M28: 1097 | N28: 1150 | O28: 884 | P28: 1477 | Q28: 1709 | R28: 6317
A29: OI0000028 | B29: ORD000875 | C29: =_xlfn.XLOOKUP(order_items[[#This Row],[order_id]],orders!A:A,orders!C:C) -> 45329 | D29: =YEAR(order_items[[#This Row],[Date]])&"-"&TEXT(MONTH(order_items[[#This Row],[Date]]),"00") -> 2024-02 | E29: =_xlfn.XLOOKUP(order_items[[#This Row],[product_id]],products!A:A,products!C:C) -> Outdoor & Sports | F29: P0182 | G29: WH06 | H29: 11 | I29: 220.15 | J29: 0.15 | L29: 2023-11 | M29: 1167 | N29: 1200 | O29: 946 | P29: 1017 | Q29: 1687 | R29: 6017
A30: OI0000029 | B30: ORD000802 | C30: =_xlfn.XLOOKUP(order_items[[#This Row],[order_id]],orders!A:A,orders!C:C) -> 45466 | D30: =YEAR(order_items[[#This Row],[Date]])&"-"&TEXT(MONTH(order_items[[#This Row],[Date]]),"00") -> 2024-06 | E30: =_xlfn.XLOOKUP(order_items[[#This Row],[product_id]],products!A:A,products!C:C) -> Health & Beauty | F30: P0198 | G30: WH09 | H30: 17 | I30: 301.5 | J30: 0 | L30: 2023-12 | M30: 1125 | N30: 1190 | O30: 1076 | P30: 1392 | Q30: 2011 | R30: 6794
... A42: OI0000041 | B42: ORD004418 | C42: =_xlfn.XLOOKUP(order_items[[#This Row],[order_id]],orders!A:A,orders!C:C) -> 45094 | D42: =YEAR(order_items[[#This Row],[Date]])&"-"&TEXT(MONTH(order_items[[#This Row],[Date]]),"00") -> 2023-06 | E42: =_xlfn.XLOOKUP(order_items[[#This Row],[product_id]],products!A:A,products!C:C) -> Electronics | F42: P0055 | G42: WH06 | H42: 18 | I42: 163.53 | J42: 0.1 | L42: Grand Total | M42: 25053 | N42: 25843 | O42: 22224 | P42: 31099 | Q42: 37792 | R42: 142011
A43: OI0000042 | B43: ORD000563 | C43: =_xlfn.XLOOKUP(order_items[[#This Row],[order_id]],orders!A:A,orders!C:C) -> 45035 | D43: =YEAR(order_items[[#This Row],[Date]])&"-"&TEXT(MONTH(order_items[[#This Row],[Date]]),"00") -> 2023-04 | E43: =_xlfn.XLOOKUP(order_items[[#This Row],[product_id]],products!A:A,products!C:C) -> Electronics | F43: P0187 | G43: WH04 | H43: 23 | I43: 312.08 | J43: 0
A44: OI0000043 | B44: ORD000563 | C44: =_xlfn.XLOOKUP(order_items[[#This Row],[order_id]],orders!A:A,orders!C:C) -> 45035 | D44: =YEAR(order_items[[#This Row],[Date]])&"-"&TEXT(MONTH(order_items[[#This Row],[Date]]),"00") -> 2023-04 | E44: =_xlfn.XLOOKUP(order_items[[#This Row],[product_id]],products!A:A,products!C:C) -> Outdoor & Sports | F44: P0169 | G44: WH08 | H44: 23 | I44: 294.41 | J44: 0.15
A45: OI0000044 | B45: ORD000289 | C45: =_xlfn.XLOOKUP(order_items[[#This Row],[order_id]],orders!A:A,orders!C:C) -> 45031 | D45: =YEAR(order_items[[#This Row],[Date]])&"-"&TEXT(MONTH(order_items[[#This Row],[Date]]),"00") -> 2023-04 | E45: =_xlfn.XLOOKUP(order_items[[#This Row],[product_id]],products!A:A,products!C:C) -> Outdoor & Sports | F45: P0069 | G45: WH01 | H45: 10 | I45: 260.81 | J45: 0.1
A46: OI0000045 | B46: ORD005641 | C46: =_xlfn.XLOOKUP(order_items[[#This Row],[order_id]],orders!A:A,orders!C:C) -> 45346 | D46: =YEAR(order_items[[#This Row],[Date]])&"-"&TEXT(MONTH(order_items[[#This Row],[Date]]),"00") -> 2024-02 | E46: =_xlfn.XLOOKUP(order_items[[#This Row],[product_id]],products!A:A,products!C:C) -> Outdoor & Sports | F46: P0004 | G46: WH07 | H46: 15 | I46: 424.37 | J46: 0.1
A47: OI0000046 | B47: ORD005650 | C47: =_xlfn.XLOOKUP(order_items[[#This Row],[order_id]],orders!A:A,orders!C:C) -> 45041 | D47: =YEAR(order_items[[#This Row],[Date]])&"-"&TEXT(MONTH(order_items[[#This Row],[Date]]),"00") -> 2023-04 | E47: =_xlfn.XLOOKUP(order_items[[#This Row],[product_id]],products!A:A,products!C:C) -> Health & Beauty | F47: P0113 | G47: WH10 | H47: 8 | I47: 98.57 | J47: 0.05
A48: OI0000047 | B48: ORD005650 | C48: =_xlfn.XLOOKUP(order_items[[#This Row],[order_id]],orders!A:A,orders!C:C) -> 45041 | D48: =YEAR(order_items[[#This Row],[Date]])&"-"&TEXT(MONTH(order_items[[#This Row],[Date]]),"00") -> 2023-04 | E48: =_xlfn.XLOOKUP(order_items[[#This Row],[product_id]],products!A:A,products!C:C) -> Office Supplies | F48: P0039 | G48: WH09 | H48: 1 | I48: 207.47 | J48: 0 | L48: Row Labels | M48: Average of unit_price
A49: OI0000048 | B49: ORD003814 | C49: =_xlfn.XLOOKUP(order_items[[#This Row],[order_id]],orders!A:A,orders!C:C) -> 44984 | D49: =YEAR(order_items[[#This Row],[Date]])&"-"&TEXT(MONTH(order_items[[#This Row],[Date]]),"00") -> 2023-02 | E49: =_xlfn.XLOOKUP(order_items[[#This Row],[product_id]],products!A:A,products!C:C) -> Outdoor & Sports | F49: P0110 | G49: WH10 | H49: 6 | I49: 118.24 | J49: 0.05 | L49: Electronics | M49: 227.5842
A50: OI0000049 | B50: ORD003176 | C50: =_xlfn.XLOOKUP(order_items[[#This Row],[order_id]],orders!A:A,orders!C:C) -> 45239 | D50: =YEAR(order_items[[#This Row],[Date]])&"-"&TEXT(MONTH(order_items[[#This Row],[Date]]),"00") -> 2023-11 | E50: =_xlfn.XLOOKUP(order_items[[#This Row],[product_id]],products!A:A,products!C:C) -> Health & Beauty | F50: P0010 | G50: WH02 | H50: 7 | I50: 86.23 | J50: 0 | L50: Health & Beauty | M50: 274.91569
A51: OI0000050 | B51: ORD003176 | C51: =_xlfn.XLOOKUP(order_items[[#This Row],[order_id]],orders!A:A,orders!C:C) -> 45239 | D51: =YEAR(order_items[[#This Row],[Date]])&"-"&TEXT(MONTH(order_items[[#This Row],[Date]]),"00") -> 2023-11 | E51: =_xlfn.XLOOKUP(order_items[[#This Row],[product_id]],products!A:A,products!C:C) -> Electronics | F51: P0118 | G51: WH05 | H51: 16 | I51: 237.19 | J51: 0.1 | L51: Home & Kitchen | M51: 245.43526
A52: OI0000051 | B52: ORD002824 | C52: =_xlfn.XLOOKUP(order_items[[#This Row],[order_id]],orders!A:A,orders!C:C) -> 44979 | D52: =YEAR(order_items[[#This Row],[Date]])&"-"&TEXT(MONTH(order_items[[#This Row],[Date]]),"00") -> 2023-02 | E52: =_xlfn.XLOOKUP(order_items[[#This Row],[product_id]],products!A:A,products!C:C) -> Health & Beauty | F52: P0198 | G52: WH10 | H52: 10 | I52: 301.5 | J52: 0.15 | L52: Office Supplies | M52: 238.86224
A53: OI0000052 | B53: ORD002824 | C53: =_xlfn.XLOOKUP(order_items[[#This Row],[order_id]],orders!A:A,orders!C:C) -> 44979 | D53: =YEAR(order_items[[#This Row],[Date]])&"-"&TEXT(MONTH(order_items[[#This Row],[Date]]),"00") -> 2023-02 | E53: =_xlfn.XLOOKUP(order_items[[#This Row],[product_id]],products!A:A,products!C:C) -> Office Supplies | F53: P0092 | G53: WH09 | H53: 12 | I53: 84.97 | J53: 0 | L53: Outdoor & Sports | M53: 242.83236
A54: OI0000053 | B54: ORD002314 | C54: =_xlfn.XLOOKUP(order_items[[#This Row],[order_id]],orders!A:A,orders!C:C) -> 45203 | D54: =YEAR(order_items[[#This Row],[Date]])&"-"&TEXT(MONTH(order_items[[#This Row],[Date]]),"00") -> 2023-10 | E54: =_xlfn.XLOOKUP(order_items[[#This Row],[product_id]],products!A:A,products!C:C) -> Office Supplies | F54: P0077 | G54: WH09 | H54: 3 | I54: 112.25 | J54: 0 | L54: Grand Total | M54: 245.61389
A55: OI0000054 | B55: ORD003871 | C55: =_xlfn.XLOOKUP(order_items[[#This Row],[order_id]],orders!A:A,orders!C:C) -> 44963 | D55: =YEAR(order_items[[#This Row],[Date]])&"-"&TEXT(MONTH(order_items[[#This Row],[Date]]),"00") -> 2023-02 | E55: =_xlfn.XLOOKUP(order_items[[#This Row],[product_id]],products!A:A,products!C:C) -> Outdoor & Sports | F55: P0084 | G55: WH04 | H55: 23 | I55: 485.61 | J55: 0.15
A56: OI0000055 | B56: ORD000815 | C56: =_xlfn.XLOOKUP(order_items[[#This Row],[order_id]],orders!A:A,orders!C:C) -> 45162 | D56: =YEAR(order_items[[#This Row],[Date]])&"-"&TEXT(MONTH(order_items[[#This Row],[Date]]),"00") -> 2023-08 | E56: =_xlfn.XLOOKUP(order_items[[#This Row],[product_id]],products!A:A,products!C:C) -> Electronics | F56: P0017 | G56: WH10 | H56: 25 | I56: 13.62 | J56: 0.1
A57: OI0000056 | B57: ORD000815 | C57: =_xlfn.XLOOKUP(order_items[[#This Row],[order_id]],orders!A:A,orders!C:C) -> 45162 | D57: =YEAR(order_items[[#This Row],[Date]])&"-"&TEXT(MONTH(order_items[[#This Row],[Date]]),"00") -> 2023-08 | E57: =_xlfn.XLOOKUP(order_items[[#This Row],[product_id]],products!A:A,products!C:C) -> Home & Kitchen | F57: P0021 | G57: WH07 | H57: 8 | I57: 297.11 | J57: 0.15
A58: OI0000057 | B58: ORD000815 | C58: =_xlfn.XLOOKUP(order_items[[#This Row],[order_id]],orders!A:A,orders!C:C) -> 45162 | D58: =YEAR(order_items[[#This Row],[Date]])&"-"&TEXT(MONTH(order_items[[#This Row],[Date]]),"00") -> 2023-08 | E58: =_xlfn.XLOOKUP(order_items[[#This Row],[product_id]],products!A:A,products!C:C) -> Home & Kitchen | F58: P0170 | G58: WH04 | H58: 2 | I58: 353.63 | J58: 0.15
A59: OI0000058 | B59: ORD000815 | C59: =_xlfn.XLOOKUP(order_items[[#This Row],[order_id]],orders!A:A,orders!C:C) -> 45162 | D59: =YEAR(order_items[[#This Row],[Date]])&"-"&TEXT(MONTH(order_items[[#This Row],[Date]]),"00") -> 2023-08 | E59: =_xlfn.XLOOKUP(order_items[[#This Row],[product_id]],products!A:A,products!C:C) -> Office Supplies | F59: P0125 | G59: WH02 | H59: 11 | I59: 122.56 | J59: 0
A60: OI0000059 | B60: ORD001126 | C60: =_xlfn.XLOOKUP(order_items[[#This Row],[order_id]],orders!A:A,orders!C:C) -> 45070 | D60: =YEAR(order_items[[#This Row],[Date]])&"-"&TEXT(MONTH(order_items[[#This Row],[Date]]),"00") -> 2023-05 | E60: =_xlfn.XLOOKUP(order_items[[#This Row],[product_id]],products!A:A,products!C:C) -> Office Supplies | F60: P0109 | G60: WH06 | H60: 3 | I60: 469.16 | J60: 0
A61: OI0000060 | B61: ORD002483 | C61: =_xlfn.XLOOKUP(order_items[[#This Row],[order_id]],orders!A:A,orders!C:C) -> 45144 | D61: =YEAR(order_items[[#This Row],[Date]])&"-"&TEXT(MONTH(order_items[[#This Row],[Date]]),"00") -> 2023-08 | E61: =_xlfn.XLOOKUP(order_items[[#This Row],[product_id]],products!A:A,products!C:C) -> Electronics | F61: P0166 | G61: WH07 | H61: 3 | I61: 160.59 | J61: 0
A62: OI0000061 | B62: ORD002449 | C62: =_xlfn.XLOOKUP(order_items[[#This Row],[order_id]],orders!A:A,orders!C:C) -> 45460 | D62: =YEAR(order_items[[#This Row],[Date]])&"-"&TEXT(MONTH(order_items[[#This Row],[Date]]),"00") -> 2024-06 | E62: =_xlfn.XLOOKUP(order_items[[#This Row],[product_id]],products!A:A,products!C:C) -> Electronics | F62: P0046 | G62: WH08 | H62: 14 | I62: 46.81 | J62: 0.1
A63: OI0000062 | B63: ORD004155 | C63: =_xlfn.XLOOKUP(order_items[[#This Row],[order_id]],orders!A:A,orders!C:C) -> 45149 | D63: =YEAR(order_items[[#This Row],[Date]])&"-"&TEXT(MONTH(order_items[[#This Row],[Date]]),"00") -> 2023-08 | E63: =_xlfn.XLOOKUP(order_items[[#This Row],[product_id]],products!A:A,products!C:C) -> Outdoor & Sports | F63: P0086 | G63: WH08 | H63: 17 | I63: 316.57 | J63: 0
A64: OI0000063 | B64: ORD005273 | C64: =_xlfn.XLOOKUP(order_items[[#This Row],[order_id]],orders!A:A,orders!C:C) -> 45215 | D64: =YEAR(order_items[[#This Row],[Date]])&"-"&TEXT(MONTH(order_items[[#This Row],[Date]]),"00") -> 2023-10 | E64: =_xlfn.XLOOKUP(order_items[[#This Row],[product_id]],products!A:A,products!C:C) -> Electronics | F64: P0131 | G64: WH02 | H64: 14 | I64: 358.06 | J64: 0
A65: OI0000064 | B65: ORD005273 | C65: =_xlfn.XLOOKUP(order_items[[#This Row],[order_id]],orders!A:A,orders!C:C) -> 45215 | D65: =YEAR(order_items[[#This Row],[Date]])&"-"&TEXT(MONTH(order_items[[#This Row],[Date]]),"00") -> 2023-10 | E65: =_xlfn.XLOOKUP(order_items[[#This Row],[product_id]],products!A:A,products!C:C) -> Home & Kitchen | F65: P0021 | G65: WH05 | H65: 19 | I65: 297.11 | J65: 0.1
A66: OI0000065 | B66: ORD005273 | C66: =_xlfn.XLOOKUP(order_items[[#This Row],[order_id]],orders!A:A,orders!C:C) -> 45215 | D66: =YEAR(order_items[[#This Row],[Date]])&"-"&TEXT(MONTH(order_items[[#This Row],[Date]]),"00") -> 2023-10 | E66: =_xlfn.XLOOKUP(order_items[[#This Row],[product_id]],products!A:A,products!C:C) -> Outdoor & Sports | F66: P0110 | G66: WH09 | H66: 23 | I66: 118.24 | J66: 0
... A71: OI0000070 | B71: ORD004746 | C71: =_xlfn.XLOOKUP(order_items[[#This Row],[order_id]],orders!A:A,orders!C:C) -> 45024 | D71: =YEAR(order_items[[#This Row],[Date]])&"-"&TEXT(MONTH(order_items[[#This Row],[Date]]),"00") -> 2023-04 | E71: =_xlfn.XLOOKUP(order_items[[#This Row],[product_id]],products!A:A,products!C:C) -> Office Supplies | F71: P0039 | G71: WH07 | H71: 16 | I71: 207.47 | J71: 0
A72: OI0000071 | B72: ORD005990 | C72: =_xlfn.XLOOKUP(order_items[[#This Row],[order_id]],orders!A:A,orders!C:C) -> 45231 | D72: =YEAR(order_items[[#This Row],[Date]])&"-"&TEXT(MONTH(order_items[[#This Row],[Date]]),"00") -> 2023-11 | E72: =_xlfn.XLOOKUP(order_items[[#This Row],[product_id]],products!A:A,products!C:C) -> Office Supplies | F72: P0103 | G72: WH06 | H72: 25 | I72: 202.31 | J72: 0.1 | N72: Month | O72: Home &Kitchen | P72: Simple Exponential Smoothing
A73: OI0000072 | B73: ORD001146 | C73: =_xlfn.XLOOKUP(order_items[[#This Row],[order_id]],orders!A:A,orders!C:C) -> 45316 | D73: =YEAR(order_items[[#This Row],[Date]])&"-"&TEXT(MONTH(order_items[[#This Row],[Date]]),"00") -> 2024-01 | E73: =_xlfn.XLOOKUP(order_items[[#This Row],[product_id]],products!A:A,products!C:C) -> Office Supplies | F73: P0151 | G73: WH02 | H73: 5 | I73: 386.19 | J73: 0.1 | N73: 44927 | O73: 945 | P73: 945
A74: OI0000073 | B74: ORD000214 | C74: =_xlfn.XLOOKUP(order_items[[#This Row],[order_id]],orders!A:A,orders!C:C) -> 45372 | D74: =YEAR(order_items[[#This Row],[Date]])&"-"&TEXT(MONTH(order_items[[#This Row],[Date]]),"00") -> 2024-03 | E74: =_xlfn.XLOOKUP(order_items[[#This Row],[product_id]],products!A:A,products!C:C) -> Health & Beauty | F74: P0195 | G74: WH07 | H74: 25 | I74: 272.63 | N74: 44958 | O74: 1183 | P74: 945
A75: OI0000074 | B75: ORD005496 | C75: =_xlfn.XLOOKUP(order_items[[#This Row],[order_id]],orders!A:A,orders!C:C) -> 45043 | D75: =YEAR(order_items[[#This Row],[Date]])&"-"&TEXT(MONTH(order_items[[#This Row],[Date]]),"00") -> 2023-04 | E75: =_xlfn.XLOOKUP(order_items[[#This Row],[product_id]],products!A:A,products!C:C) -> Outdoor & Sports | F75: P0145 | G75: WH09 | H75: 7 | I75: 224.38 | J75: 0 | N75: 44986 | O75: 1085 | P75: 1016.4
A76: OI0000075 | B76: ORD005496 | C76: =_xlfn.XLOOKUP(order_items[[#This Row],[order_id]],orders!A:A,orders!C:C) -> 45043 | D76: =YEAR(order_items[[#This Row],[Date]])&"-"&TEXT(MONTH(order_items[[#This Row],[Date]]),"00") -> 2023-04 | E76: =_xlfn.XLOOKUP(order_items[[#This Row],[product_id]],products!A:A,products!C:C) -> Health & Beauty | F76: P0200 | G76: WH02 | H76: 7 | I76: 377.95 | J76: 0 | N76: 45017 | O76: 997 | P76: 1037
A77: OI0000076 | B77: ORD001692 | C77: =_xlfn.XLOOKUP(order_items[[#This Row],[order_id]],orders!A:A,orders!C:C) -> 45317 | D77: =YEAR(order_items[[#This Row],[Date]])&"-"&TEXT(MONTH(order_items[[#This Row],[Date]]),"00") -> 2024-01 | E77: =_xlfn.XLOOKUP(order_items[[#This Row],[product_id]],products!A:A,products!C:C) -> Office Supplies | F77: P0064 | G77: WH03 | H77: 21 | I77: 172.43 | J77: 0 | N77: 45047 | O77: 866 | P77: 1025
A78: OI0000077 | B78: ORD001428 | C78: =_xlfn.XLOOKUP(order_items[[#This Row],[order_id]],orders!A:A,orders!C:C) -> 45611 | D78: =YEAR(order_items[[#This Row],[Date]])&"-"&TEXT(MONTH(order_items[[#This Row],[Date]]),"00") -> 2024-11 | E78: =_xlfn.XLOOKUP(order_items[[#This Row],[product_id]],products!A:A,products!C:C) -> Home & Kitchen | F78: P0162 | G78: WH05 | H78: -24 | I78: 323.06 | J78: 0.05 | N78: 45078 | O78: 623 | P78: 977.3
A79: OI0000078 | B79: ORD001428 | C79: =_xlfn.XLOOKUP(order_items[[#This Row],[order_id]],orders!A:A,orders!C:C) -> 45611 | D79: =YEAR(order_items[[#This Row],[Date]])&"-"&TEXT(MONTH(order_items[[#This Row],[Date]]),"00") -> 2024-11 | E79: =_xlfn.XLOOKUP(order_items[[#This Row],[product_id]],products!A:A,products!C:C) -> Office Supplies | F79: P0045 | G79: WH01 | H79: 16 | I79: 350.18 | N79: 45108 | O79: 1014 | P79: 871
A80: OI0000079 | B80: ORD002211 | C80: =_xlfn.XLOOKUP(order_items[[#This Row],[order_id]],orders!A:A,orders!C:C) -> 45448 | D80: =YEAR(order_items[[#This Row],[Date]])&"-"&TEXT(MONTH(order_items[[#This Row],[Date]]),"00") -> 2024-06 | E80: =_xlfn.XLOOKUP(order_items[[#This Row],[product_id]],products!A:A,products!C:C) -> Electronics | F80: P0138 | G80: WH07 | H80: -3 | I80: 152.98 | J80: 0 | N80: 45139 | O80: 964 | P80: 913.9
A81: OI0000080 | B81: ORD001117 | C81: =_xlfn.XLOOKUP(order_items[[#This Row],[order_id]],orders!A:A,orders!C:C) -> 45380 | D81: =YEAR(order_items[[#This Row],[Date]])&"-"&TEXT(MONTH(order_items[[#This Row],[Date]]),"00") -> 2024-03 | E81: =_xlfn.XLOOKUP(order_items[[#This Row],[product_id]],products!A:A,products!C:C) -> Home & Kitchen | F81: P0024 | G81: WH05 | H81: 15 | I81: 190.51 | J81: 0.1 | N81: 45170 | O81: 1056 | P81: 928.9
A82: OI0000081 | B82: ORD004081 | C82: =_xlfn.XLOOKUP(order_items[[#This Row],[order_id]],orders!A:A,orders!C:C) -> 45449 | D82: =YEAR(order_items[[#This Row],[Date]])&"-"&TEXT(MONTH(order_items[[#This Row],[Date]]),"00") -> 2024-06 | E82: =_xlfn.XLOOKUP(order_items[[#This Row],[product_id]],products!A:A,products!C:C) -> Electronics | F82: P0160 | G82: WH08 | H82: 23 | I82: 158.65 | J82: 0 | N82: 45200 | O82: 884 | P82: 967
A83: OI0000082 | B83: ORD000585 | C83: =_xlfn.XLOOKUP(order_items[[#This Row],[order_id]],orders!A:A,orders!C:C) -> 44989 | D83: =YEAR(order_items[[#This Row],[Date]])&"-"&TEXT(MONTH(order_items[[#This Row],[Date]]),"00") -> 2023-03 | E83: =_xlfn.XLOOKUP(order_items[[#This Row],[product_id]],products!A:A,products!C:C) -> Health & Beauty | F83: P0200 | G83: WH03 | H83: -12 | I83: 377.95 | J83: 0.15 | N83: 45231 | O83: 946 | P83: 942.1
A84: OI0000083 | B84: ORD000585 | C84: =_xlfn.XLOOKUP(order_items[[#This Row],[order_id]],orders!A:A,orders!C:C) -> 44989 | D84: =YEAR(order_items[[#This Row],[Date]])&"-"&TEXT(MONTH(order_items[[#This Row],[Date]]),"00") -> 2023-03 | E84: =_xlfn.XLOOKUP(order_items[[#This Row],[product_id]],products!A:A,products!C:C) -> Outdoor & Sports | F84: P0106 | G84: WH10 | H84: 12 | I84: 213.2 | J84: 0 | N84: 45261 | O84: 1076 | P84: 943.3
A85: OI0000084 | B85: ORD002415 | C85: =_xlfn.XLOOKUP(order_items[[#This Row],[order_id]],orders!A:A,orders!C:C) -> 45112 | D85: =YEAR(order_items[[#This Row],[Date]])&"-"&TEXT(MONTH(order_items[[#This Row],[Date]]),"00") -> 2023-07 | E85: =_xlfn.XLOOKUP(order_items[[#This Row],[product_id]],products!A:A,products!C:C) -> Home & Kitchen | F85: P0052 | G85: WH03 | H85: 12 | I85: 85.3 | J85: 0 | N85: 45292 | O85: 931 | P85: 983.1
A86: OI0000085 | B86: ORD004806 | C86: =_xlfn.XLOOKUP(order_items[[#This Row],[order_id]],orders!A:A,orders!C:C) -> 45411 | D86: =YEAR(order_items[[#This Row],[Date]])&"-"&TEXT(MONTH(order_items[[#This Row],[Date]]),"00") -> 2024-04 | E86: =_xlfn.XLOOKUP(order_items[[#This Row],[product_id]],products!A:A,products!C:C) -> Office Supplies | F86: P0019 | G86: WH10 | H86: 24 | I86: 203.36 | J86: 0 | N86: 45323 | O86: 840 | P86: 967.5
A87: OI0000086 | B87: ORD004806 | C87: =_xlfn.XLOOKUP(order_items[[#This Row],[order_id]],orders!A:A,orders!C:C) -> 45411 | D87: =YEAR(order_items[[#This Row],[Date]])&"-"&TEXT(MONTH(order_items[[#This Row],[Date]]),"00") -> 2024-04 | E87: =_xlfn.XLOOKUP(order_items[[#This Row],[product_id]],products!A:A,products!C:C) -> Home & Kitchen | F87: P0152 | G87: WH01 | H87: 25 | I87: 336.63 | J87: 0 | N87: 45352 | O87: 1021 | P87: 929.3
A88: OI0000087 | B88: ORD004806 | C88: =_xlfn.XLOOKUP(order_items[[#This Row],[order_id]],orders!A:A,orders!C:C) -> 45411 | D88: =YEAR(order_items[[#This Row],[Date]])&"-"&TEXT(MONTH(order_items[[#This Row],[Date]]),"00") -> 2024-04 | E88: =_xlfn.XLOOKUP(order_items[[#This Row],[product_id]],products!A:A,products!C:C) -> Home & Kitchen | F88: P0119 | G88: WH05 | H88: 25 | I88: 475.7 | J88: 0.15 | N88: 45383 | O88: 868 | P88: 956.8
A89: OI0000088 | B89: ORD004806 | C89: =_xlfn.XLOOKUP(order_items[[#This Row],[order_id]],orders!A:A,orders!C:C) -> 45411 | D89: =YEAR(order_items[[#This Row],[Date]])&"-"&TEXT(MONTH(order_items[[#This Row],[Date]]),"00") -> 2024-04 | E89: =_xlfn.XLOOKUP(order_items[[#This Row],[product_id]],products!A:A,products!C:C) -> Outdoor & Sports | F89: P0102 | G89: WH07 | H89: 10 | I89: 358.43 | J89: 0.1 | N89: 45413 | O89: 1094 | P89: 930.2
A90: OI0000089 | B90: ORD003945 | C90: =_xlfn.XLOOKUP(order_items[[#This Row],[order_id]],orders!A:A,orders!C:C) -> 45082 | D90: =YEAR(order_items[[#This Row],[Date]])&"-"&TEXT(MONTH(order_items[[#This Row],[Date]]),"00") -> 2023-06 | E90: =_xlfn.XLOOKUP(order_items[[#This Row],[product_id]],products!A:A,products!C:C) -> Health & Beauty | F90: P0030 | G90: WH04 | H90: 16 | I90: 246.7 | J90: 0 | N90: 45444 | O90: 1079 | P90: 979.3
A91: OI0000090 | B91: ORD005318 | C91: =_xlfn.XLOOKUP(order_items[[#This Row],[order_id]],orders!A:A,orders!C:C) -> 45238 | D91: =YEAR(order_items[[#This Row],[Date]])&"-"&TEXT(MONTH(order_items[[#This Row],[Date]]),"00") -> 2023-11 | E91: =_xlfn.XLOOKUP(order_items[[#This Row],[product_id]],products!A:A,products!C:C) -> Health & Beauty | F91: P0034 | G91: WH10 | H91: 7 | I91: 306.07 | J91: 0 | N91: 45474 | O91: 861 | P91: 1009.2
... A95: OI0000094 | B95: ORD000028 | C95: =_xlfn.XLOOKUP(order_items[[#This Row],[order_id]],orders!A:A,orders!C:C) -> 45596 | D95: =YEAR(order_items[[#This Row],[Date]])&"-"&TEXT(MONTH(order_items[[#This Row],[Date]]),"00") -> 2024-10 | E95: =_xlfn.XLOOKUP(order_items[[#This Row],[product_id]],products!A:A,products!C:C) -> Outdoor & Sports | F95: P0176 | G95: WH09 | H95: 21 | I95: 41.57 | J95: 0.1 | N95: 45597 | O95: 982 | P95: 925.6
A96: OI0000095 | B96: ORD001776 | C96: =_xlfn.XLOOKUP(order_items[[#This Row],[order_id]],orders!A:A,orders!C:C) -> 45380 | D96: =YEAR(order_items[[#This Row],[Date]])&"-"&TEXT(MONTH(order_items[[#This Row],[Date]]),"00") -> 2024-03 | E96: =_xlfn.XLOOKUP(order_items[[#This Row],[product_id]],products!A:A,products!C:C) -> Electronics | F96: P0160 | G96: WH06 | H96: 25 | I96: 158.65 | J96: 0
A97: OI0000096 | B97: ORD000266 | C97: =_xlfn.XLOOKUP(order_items[[#This Row],[order_id]],orders!A:A,orders!C:C) -> 45457 | D97: =YEAR(order_items[[#This Row],[Date]])&"-"&TEXT(MONTH(order_items[[#This Row],[Date]]),"00") -> 2024-06 | E97: =_xlfn.XLOOKUP(order_items[[#This Row],[product_id]],products!A:A,products!C:C) -> Home & Kitchen | F97: P0005 | G97: WH02 | H97: 5 | I97: 253.72 | J97: 0.1
A98: OI0000097 | B98: ORD000266 | C98: =_xlfn.XLOOKUP(order_items[[#This Row],[order_id]],orders!A:A,orders!C:C) -> 45457 | D98: =YEAR(order_items[[#This Row],[Date]])&"-"&TEXT(MONTH(order_items[[#This Row],[Date]]),"00") -> 2024-06 | E98: =_xlfn.XLOOKUP(order_items[[#This Row],[product_id]],products!A:A,products!C:C) -> Electronics | F98: P0018 | G98: WH06 | H98: 9 | I98: 233.95 | J98: 0.1
A99: OI0000098 | B99: ORD001576 | C99: =_xlfn.XLOOKUP(order_items[[#This Row],[order_id]],orders!A:A,orders!C:C) -> 45555 | D99: =YEAR(order_items[[#This Row],[Date]])&"-"&TEXT(MONTH(order_items[[#This Row],[Date]]),"00") -> 2024-09 | E99: =_xlfn.XLOOKUP(order_items[[#This Row],[product_id]],products!A:A,products!C:C) -> Office Supplies | F99: P0087 | G99: WH06 | H99: 19 | I99: 188.01 | J99: 0
A100: OI0000099 | B100: ORD002213 | C100: =_xlfn.XLOOKUP(order_items[[#This Row],[order_id]],orders!A:A,orders!C:C) -> 45242 | D100: =YEAR(order_items[[#This Row],[Date]])&"-"&TEXT(MONTH(order_items[[#This Row],[Date]]),"00") -> 2023-11 | E100: =_xlfn.XLOOKUP(order_items[[#This Row],[product_id]],products!A:A,products!C:C) -> Electronics | F100: P0187 | G100: WH06 | H100: 16 | I100: 312.08 | J100: 0.1
A101: OI0000100 | B101: ORD002207 | C101: =_xlfn.XLOOKUP(order_items[[#This Row],[order_id]],orders!A:A,orders!C:C) -> 45559 | D101: =YEAR(order_items[[#This Row],[Date]])&"-"&TEXT(MONTH(order_items[[#This Row],[Date]]),"00") -> 2024-09 | E101: =_xlfn.XLOOKUP(order_items[[#This Row],[product_id]],products!A:A,products!C:C) -> Office Supplies | F101: P0151 | G101: WH03 | H101: 4 | I101: 386.19 | J101: 0
A102: OI0000101 | B102: ORD002207 | C102: =_xlfn.XLOOKUP(order_items[[#This Row],[order_id]],orders!A:A,orders!C:C) -> 45559 | D102: =YEAR(order_items[[#This Row],[Date]])&"-"&TEXT(MONTH(order_items[[#This Row],[Date]]),"00") -> 2024-09 | E102: =_xlfn.XLOOKUP(order_items[[#This Row],[product_id]],products!A:A,products!C:C) -> Home & Kitchen | F102: P0146 | G102: WH01 | H102: 2 | I102: 152.2 | J102: 0
A103: OI0000102 | B103: ORD001827 | C103: =_xlfn.XLOOKUP(order_items[[#This Row],[order_id]],orders!A:A,orders!C:C) -> 45305 | D103: =YEAR(order_items[[#This Row],[Date]])&"-"&TEXT(MONTH(order_items[[#This Row],[Date]]),"00") -> 2024-01 | E103: =_xlfn.XLOOKUP(order_items[[#This Row],[product_id]],products!A:A,products!C:C) -> Office Supplies | F103: P0019 | G103: WH02 | H103: 24 | I103: 203.36 | J103: 0
A104: OI0000103 | B104: ORD001827 | C104: =_xlfn.XLOOKUP(order_items[[#This Row],[order_id]],orders!A:A,orders!C:C) -> 45305 | D104: =YEAR(order_items[[#This Row],[Date]])&"-"&TEXT(MONTH(order_items[[#This Row],[Date]]),"00") -> 2024-01 | E104: =_xlfn.XLOOKUP(order_items[[#This Row],[product_id]],products!A:A,products!C:C) -> Office Supplies | F104: P0064 | G104: WH05 | H104: 5 | I104: 172.43
A105: OI0000104 | B105: ORD000089 | C105: =_xlfn.XLOOKUP(order_items[[#This Row],[order_id]],orders!A:A,orders!C:C) -> 45391 | D105: =YEAR(order_items[[#This Row],[Date]])&"-"&TEXT(MONTH(order_items[[#This Row],[Date]]),"00") -> 2024-04 | E105: =_xlfn.XLOOKUP(order_items[[#This Row],[product_id]],products!A:A,products!C:C) -> Office Supplies | F105: P0125 | G105: WH09 | H105: 20 | I105: 122.56 | J105: 0
A106: OI0000105 | B106: ORD001449 | C106: =_xlfn.XLOOKUP(order_items[[#This Row],[order_id]],orders!A:A,orders!C:C) -> 44968 | D106: =YEAR(order_items[[#This Row],[Date]])&"-"&TEXT(MONTH(order_items[[#This Row],[Date]]),"00") -> 2023-02 | E106: =_xlfn.XLOOKUP(order_items[[#This Row],[product_id]],products!A:A,products!C:C) -> Office Supplies | F106: P0111 | G106: WH07 | H106: 11 | I106: 436.43 | J106: 0
A107: OI0000106 | B107: ORD001238 | C107: =_xlfn.XLOOKUP(order_items[[#This Row],[order_id]],orders!A:A,orders!C:C) -> 44986 | D107: =YEAR(order_items[[#This Row],[Date]])&"-"&TEXT(MONTH(order_items[[#This Row],[Date]]),"00") -> 2023-03 | E107: =_xlfn.XLOOKUP(order_items[[#This Row],[product_id]],products!A:A,products!C:C) -> Electronics | F107: P0133 | G107: WH05 | H107: 6 | I107: 237.27 | J107: 0.15
A108: OI0000107 | B108: ORD001238 | C108: =_xlfn.XLOOKUP(order_items[[#This Row],[order_id]],orders!A:A,orders!C:C) -> 44986 | D108: =YEAR(order_items[[#This Row],[Date]])&"-"&TEXT(MONTH(order_items[[#This Row],[Date]]),"00") -> 2023-03 | E108: =_xlfn.XLOOKUP(order_items[[#This Row],[product_id]],products!A:A,products!C:C) -> Outdoor & Sports | F108: P0099 | G108: WH08 | H108: 4 | I108: 230.33 | J108: 0
A109: OI0000108 | B109: ORD001238 | C109: =_xlfn.XLOOKUP(order_items[[#This Row],[order_id]],orders!A:A,orders!C:C) -> 44986 | D109: =YEAR(order_items[[#This Row],[Date]])&"-"&TEXT(MONTH(order_items[[#This Row],[Date]]),"00") -> 2023-03 | E109: =_xlfn.XLOOKUP(order_items[[#This Row],[product_id]],products!A:A,products!C:C) -> Health & Beauty | F109: P0037 | G109: WH07 | H109: 7 | I109: 332.27 | J109: 0
A110: OI0000109 | B110: ORD001238 | C110: =_xlfn.XLOOKUP(order_items[[#This Row],[order_id]],orders!A:A,orders!C:C) -> 44986 | D110: =YEAR(order_items[[#This Row],[Date]])&"-"&TEXT(MONTH(order_items[[#This Row],[Date]]),"00") -> 2023-03 | E110: =_xlfn.XLOOKUP(order_items[[#This Row],[product_id]],products!A:A,products!C:C) -> Electronics | F110: P0047 | G110: WH07 | H110: 25 | I110: 208.02
A111: OI0000110 | B111: ORD001750 | C111: =_xlfn.XLOOKUP(order_items[[#This Row],[order_id]],orders!A:A,orders!C:C) -> 45335 | D111: =YEAR(order_items[[#This Row],[Date]])&"-"&TEXT(MONTH(order_items[[#This Row],[Date]]),"00") -> 2024-02 | E111: =_xlfn.XLOOKUP(order_items[[#This Row],[product_id]],products!A:A,products!C:C) -> Electronics | F111: P0133 | G111: WH04 | H111: 21 | I111: 237.27 | J111: 0.15
A112: OI0000111 | B112: ORD004436 | C112: =_xlfn.XLOOKUP(order_items[[#This Row],[order_id]],orders!A:A,orders!C:C) -> 45557 | D112: =YEAR(order_items[[#This Row],[Date]])&"-"&TEXT(MONTH(order_items[[#This Row],[Date]]),"00") -> 2024-09 | E112: =_xlfn.XLOOKUP(order_items[[#This Row],[product_id]],products!A:A,products!C:C) -> Home & Kitchen | F112: P0162 | G112: WH08 | H112: 11 | I112: 323.06 | J112: 0
A113: OI0000112 | B113: ORD004436 | C113: =_xlfn.XLOOKUP(order_items[[#This Row],[order_id]],orders!A:A,orders!C:C) -> 45557 | D113: =YEAR(order_items[[#This Row],[Date]])&"-"&TEXT(MONTH(order_items[[#This Row],[Date]]),"00") -> 2024-09 | E113: =_xlfn.XLOOKUP(order_items[[#This Row],[product_id]],products!A:A,products!C:C) -> Health & Beauty | F113: P0148 | G113: WH08 | H113: 16 | I113: 175.38 | J113: 0
A114: OI0000113 | B114: ORD004436 | C114: =_xlfn.XLOOKUP(order_items[[#This Row],[order_id]],orders!A:A,orders!C:C) -> 45557 | D114: =YEAR(order_items[[#This Row],[Date]])&"-"&TEXT(MONTH(order_items[[#This Row],[Date]]),"00") -> 2024-09 | E114: =_xlfn.XLOOKUP(order_items[[#This Row],[product_id]],products!A:A,products!C:C) -> Home & Kitchen | F114: P0171 | G114: WH04 | H114: 13 | I114: 450.56 | J114: 0
A115: OI0000114 | B115: ORD004436 | C115: =_xlfn.XLOOKUP(order_items[[#This Row],[order_id]],orders!A:A,orders!C:C) -> 45557 | D115: =YEAR(order_items[[#This Row],[Date]])&"-"&TEXT(MONTH(order_items[[#This Row],[Date]]),"00") -> 2024-09 | E115: =_xlfn.XLOOKUP(order_items[[#This Row],[product_id]],products!A:A,products!C:C) -> Outdoor & Sports | F115: P0169 | G115: WH03 | H115: 18 | I115: 294.41 | J115: 0.15
A116: OI0000115 | B116: ORD003169 | C116: =_xlfn.XLOOKUP(order_items[[#This Row],[order_id]],orders!A:A,orders!C:C) -> 45166 | D116: =YEAR(order_items[[#This Row],[Date]])&"-"&TEXT(MONTH(order_items[[#This Row],[Date]]),"00") -> 2023-08 | E116: =_xlfn.XLOOKUP(order_items[[#This Row],[product_id]],products!A:A,products!C:C) -> Outdoor & Sports | F116: P0102 | G116: WH04 | H116: 6 | I116: 358.43 | J116: 0
A117: OI0000116 | B117: ORD003169 | C117: =_xlfn.XLOOKUP(order_items[[#This Row],[order_id]],orders!A:A,orders!C:C) -> 45166 | D117: =YEAR(order_items[[#This Row],[Date]])&"-"&TEXT(MONTH(order_items[[#This Row],[Date]]),"00") -> 2023-08 | E117: =_xlfn.XLOOKUP(order_items[[#This Row],[product_id]],products!A:A,products!C:C) -> Outdoor & Sports | F117: P0196 | G117: WH03 | H117: 10 | I117: 312.25 | J117: 0.05
A118: OI0000117 | B118: ORD001009 | C118: =_xlfn.XLOOKUP(order_items[[#This Row],[order_id]],orders!A:A,orders!C:C) -> 45513 | D118: =YEAR(order_items[[#This Row],[Date]])&"-"&TEXT(MONTH(order_items[[#This Row],[Date]]),"00") -> 2024-08 | E118: =_xlfn.XLOOKUP(order_items[[#This Row],[product_id]],products!A:A,products!C:C) -> Home & Kitchen | F118: P0060 | G118: WH01 | H118: 9 | I118: 255.1 | J118: 0.05
A119: OI0000118 | B119: ORD001009 | C119: =_xlfn.XLOOKUP(order_items[[#This Row],[order_id]],orders!A:A,orders!C:C) -> 45513 | D119: =YEAR(order_items[[#This Row],[Date]])&"-"&TEXT(MONTH(order_items[[#This Row],[Date]]),"00") -> 2024-08 | E119: =_xlfn.XLOOKUP(order_items[[#This Row],[product_id]],products!A:A,products!C:C) -> Outdoor & Sports | F119: P0001 | G119: WH02 | H119: 8 | I119: 440.43 | J119: 0.1
A120: OI0000119 | B120: ORD001009 | C120: =_xlfn.XLOOKUP(order_items[[#This Row],[order_id]],orders!A:A,orders!C:C) -> 45513 | D120: =YEAR(order_items[[#This Row],[Date]])&"-"&TEXT(MONTH(order_items[[#This Row],[Date]]),"00") -> 2024-08 | E120: =_xlfn.XLOOKUP(order_items[[#This Row],[product_id]],products!A:A,products!C:C) -> Office Supplies | F120: P0019 | G120: WH02 | H120: 18 | I120: 203.36 | J120: 0
...

Sheet Demand Forecast
C2: Forecast(t) = a × Actual(t-1) + (1-a) × Forecast(t-1)
E7: a | F7: =0.1 -> 0.1 | W7: a | X7: 0.28 | AK7: Category | AL7: Model | AM7: MAPE
A8: Month | B8: Category | C8: Actual | D8: SET | E8: MOVING AVG 3. MONTHS | F8: % error per month | G8: Simple Exponential Smoothing | H8: % error per month | I8: Holt-Winters Seasonal Method | J8: % error per month | S8: Month | T8: Category | U8: Actual | V8: SET | W8: MOVING AVG 3. MONTHS | X8: % error per month | Y8: Simple Exponential Smoothing | Z8: % error per month | AA8: Holt-Winters Seasonal Method | AB8: % error per month | AK8: Electronics | AL8: MOVING AVG 3. MONTHS | AM8: =O72 -> 0.18109327
A9: 44927 | B9: Outdoor & Sports | C9: 1357 | D9: TRAIN | G9: 1357 | L9: Model | M9: MAPE | S9: 44927 | T9: Health & Beauty | U9: 1114 | V9: TRAIN | Y9: 1114 | AD9: Model | AE9: MAPE | AK9: Electronics | AL9: Simple Exponential Smoothing | AM9: =O73 -> 0.17084664
A10: 44958 | B10: Outdoor & Sports | C10: 1710 | D10: TRAIN | G10: 1357 | L10: Moving Averge (3 Month) | M10: 0.16091558 | S10: 44958 | T10: Health & Beauty | U10: 1255 | V10: TRAIN | Y10: 1114 | AD10: Moving Averge (3 Month) | AE10: 0.094064971 | AK10: Electronics | AL10: Holt-Winters Seasonal Method | AM10: =O74 -> 0.15808821
A11: 44986 | B11: Outdoor & Sports | C11: 1578 | D11: TRAIN | G11: 1392.3 | L11: Simple Exponential Smoothing (a=0.5) | M11: 0.14669117 | S11: 44986 | T11: Health & Beauty | U11: 1295 | V11: TRAIN | Y11: 1153.5 | AD11: Simple Exponential Smoothing (a=0.3) | AE11: 0.086360839 | AK11: Health & Beauty | AL11: MOVING AVG 3. MONTHS | AM11: =AG17 -> 0.094064971
A12: 45017 | B12: Outdoor & Sports | C12: 1679 | D12: TRAIN | G12: 1410.9 | L12: Simple Exponential Smoothing (a=0.8) | M12: 0.1336 | S12: 45017 | T12: Health & Beauty | U12: 1114 | V12: TRAIN | Y12: 1193.1 | AD12: Simple Exponential Smoothing (a=0.28) | AE12: 0.086236091 | AK12: Health & Beauty | AL12: Simple Exponential Smoothing | AM12: =AG18 -> 0.086236091
A13: 45047 | B13: Outdoor & Sports | C13: 1672 | D13: TRAIN | G13: 1437.7 | L13: Simple Exponential Smoothing (a=0.2) | M13: 0.1336 | S13: 45047 | T13: Health & Beauty | U13: 1391 | V13: TRAIN | Y13: 1171 | AD13: Simple Exponential Smoothing (a=0.4) | AE13: 0.088523077 | AK13: Health & Beauty | AL13: Holt-Winters Seasonal Method | AM13: =AG19 -> 0.10727702
A14: 45078 | B14: Outdoor & Sports | C14: 1372 | D14: TRAIN | G14: 1461.1 | L14: Simple Exponential Smoothing (a=0.15) | M14: 0.1286 | S14: 45078 | T14: Health & Beauty | U14: 804 | V14: TRAIN | Y14: 1232.6 | AD14: Simple Exponential Smoothing (a=0.15) | AE14: 0.087951776 | AK14: Home & Kitchen | AL14: MOVING AVG 3. MONTHS | AM14: 0.19659204
A15: 45108 | B15: Outdoor & Sports | C15: 1402 | D15: TRAIN | G15: 1452.2 | L15: Simple Exponential Smoothing (a=0.1) | M15: 0.1242 | S15: 45108 | T15: Health & Beauty | U15: 876 | V15: TRAIN | Y15: 1112.6 | AD15: Simple Exponential Smoothing (a=0.1) | AE15: 0.089360883 | AK15: Home & Kitchen | AL15: Simple Exponential Smoothing | AM15: 0.16217634
A16: 45139 | B16: Outdoor & Sports | C16: 1727 | D16: TRAIN | G16: 1447.2 | L16: Simple Exponential Smoothing (a=0.05) | M16: 0.12867091 | N16: Model | O16: MAPE | P16: Total Cost (6 months) | S16: 45139 | T16: Health & Beauty | U16: 1214 | V16: TRAIN | Y16: 1046.4 | AD16: Simple Exponential Smoothing (a=0.01) | AE16: 0.087922527 | AF16: Model | AG16: MAPE | AH16: Total Cost (6 months) | AK16: Home & Kitchen | AL16: Holt-Winters Seasonal Method | AM16: 0.24810034
A17: 45170 | B17: Outdoor & Sports | C17: 1499 | D17: TRAIN | G17: 1475.2 | N17: MOVING AVG 3. MONTHS | O17: 0.16091558 | P17: 98106.3 | S17: 45170 | T17: Health & Beauty | U17: 1050 | V17: TRAIN | Y17: 1093.3 | AF17: MOVING AVG 3. MONTHS | AG17: 0.094064971 | AH17: 32390.603 | AK17: Office Supplies | AL17: MOVING AVG 3. MONTHS | AM17: =AG47 -> 0.17927731
A18: 45200 | B18: Outdoor & Sports | C18: 1709 | D18: TRAIN | G18: 1477.6 | L18: Margin | M18: 112.43245 | N18: Simple Exponential Smoothing | O18: 0.12422296 | P18: 126226.28 | S18: 45200 | T18: Health & Beauty | U18: 1150 | V18: TRAIN | Y18: 1081.2 | AD18: Margin | AE18: 122.76361 | AF18: Simple Exponential Smoothing | AG18: 0.086236091 | AH18: 20917.378 | AK18: Office Supplies | AL18: Simple Exponential Smoothing | AM18: =AG48 -> 0.14429349
A19: 45231 | B19: Outdoor & Sports | C19: 1687 | D19: TRAIN | G19: 1500.7 | L19: Holding rate | M19: 0.0167 | N19: Holt-Winters Seasonal Method | O19: 0.14694822 | P19: 97314.993 | S19: 45231 | T19: Health & Beauty | U19: 1200 | V19: TRAIN | Y19: 1100.5 | AD19: Holding rate | AE19: 0.0167 | AF19: Holt-Winters Seasonal Method | AG19: 0.10727702 | AH19: 22383.558 | AK19: Office Supplies | AL19: Holt-Winters Seasonal Method | AM19: =AG49 -> 0.12898637
A20: 45261 | B20: Outdoor & Sports | C20: 2011 | D20: TRAIN | G20: 1519.3 | L20: Unit Cost | M20: 128.27623 | S20: 45261 | T20: Health & Beauty | U20: 1190 | V20: TRAIN | Y20: 1128.4 | AD20: Unit Cost | AE20: 152.93889 | AK20: Outdoor & Sports | AL20: MOVING AVG 3. MONTHS | AM20: =O17 -> 0.16091558
A21: 45292 | B21: Outdoor & Sports | C21: 1773 | D21: TRAIN | G21: 1568.5 | S21: 45292 | T21: Health & Beauty | U21: 1348 | V21: TRAIN | Y21: 1145.6 | AK21: Outdoor & Sports | AL21: Simple Exponential Smoothing | AM21: =O18 -> 0.12422296
A22: 45323 | B22: Outdoor & Sports | C22: 1398 | D22: TRAIN | G22: 1589 | L22: Type (Moving Average) | M22: Cost Impact | N22: Type (Simple Exponential Smoothing) | O22: Cost Impact | P22: Type (Holt-Winters Seasonal Method) | Q22: Cost Impact | S22: 45323 | T22: Health & Beauty | U22: 1285 | V22: TRAIN | Y22: 1202.3 | AD22: Type (Moving Average) | AE22: Cost Impact | AF22: Type (Simple Exponential Smoothing) | AG22: Cost Impact | AH22: Type (Holt-Winters Seasonal Method) | AI22: Cost Impact | AK22: Outdoor & Sports | AL22: Holt-Winters Seasonal Method | AM22: =O19 -> 0.14694822
A23: 45352 | B23: Outdoor & Sports | C23: 1398 | D23: TRAIN | G23: 1569.9 | L23: Understock | M23: 20766.274 | N23: Understock | O23: 19293.409 | P23: Understock | Q23: 11893.931 | S23: 45352 | T23: Health & Beauty | U23: 980 | V23: TRAIN | Y23: 1225.5 | AD23: Understock | AE23: 19979.247 | AF23: Understock | AG23: 11164.543 | AH23: Understock | AI23: 14558.216
A24: 45383 | B24: Outdoor & Sports | C24: 1540 | D24: TRAIN | G24: 1552.7 | L24: Overstock | M24: 157.8811 | N24: Understock | O24: 1169.2975 | P24: Overstock | Q24: 138.93301 | S24: 45383 | T24: Health & Beauty | U24: 1035 | V24: TRAIN | Y24: 1156.8 | AD24: Overstock | AE24: 371.24551 | AF24: Overstock | AG24: 431.65592 | AH24: Overstock | AI24: 412.85278
A25: 45413 | B25: Outdoor & Sports | C25: 1731 | D25: TRAIN | G25: 1551.4 | L25: Understock | M25: 39834.818 | N25: Understock | O25: 51314.171 | P25: Understock | Q25: 44595.649 | S25: 45413 | T25: Health & Beauty | U25: 1094 | V25: TRAIN | Y25: 1122.7 | AD25: Understock | AE25: 9331.8936 | AF25: Understock | AG25: 8983.353 | AH25: Understock | AI25: 6833.817
A26: 45444 | B26: Outdoor & Sports | C26: 1741 | D26: TEST | E26: 1556.3 | F26: 0.10608845 | G26: 1569.4 | H26: 0.098564044 | I26: 1635.2126 | J26: 0.060762407 | L26: Understock | M26: 35753.52 | N26: Understock | O26: 53832.658 | P26: Understock | Q26: 39319.29 | S26: 45444 | T26: Health & Beauty | U26: 1214 | V26: TEST | W26: 1036.3 | X26: 0.14637562 | Y26: 1114.7 | Z26: 0.081795717 | AA26: 1074.3567 | AB26: 0.11502745 | AD26: Overstock | AE26: 132.8172 | AF26: Overstock | AG26: 136.03052 | AH26: Overstock | AI26: 437.52274 | AK26: Category | AL26: Model | AM26: Total Cost
A27: 45474 | B27: Outdoor & Sports | C27: 1597 | D27: TEST | E27: 1670.7 | F27: 0.046149029 | G27: 1586.6 | H27: 0.0065122104 | I27: 1661.8549 | J27: 0.040610456 | L27: Overstock | M27: 920.50892 | N27: Overstock | O27: 413.66133 | P27: Overstock | Q27: 846.93847 | S27: 45474 | T27: Health & Beauty | U27: 941 | V27: TEST | W27: 1114.3 | X27: 0.18416578 | Y27: 1142.5 | Z27: 0.2141339 | AA27: 1136.6049 | AB27: 0.2078692 | AD27: Understock | AE27: 2394.8112 | AF27: Overstock | AG27: 40.059383 | AH27: Overstock | AI27: 1.1842384 | AK27: Electronics | AL27: MOVING AVG 3. MONTHS | AM27: 50700.988
A28: 45505 | B28: Outdoor & Sports | C28: 2044 | D28: TEST | E28: 1689.7 | F28: 0.17333659 | G28: 1587.6 | H28: 0.22328767 | I28: 1647.3561 | J28: 0.1940528 | L28: Overstock | M28: 673.29754 | N28: Overstock | O28: 203.08179 | P28: Overstock | Q28: 520.25186 | S28: 45505 | T28: Health & Beauty | U28: 1166 | V28: TEST | W28: 1083 | X28: 0.071183533 | Y28: 1086.1 | Z28: 0.068524871 | AA28: 1100.4496 | AB28: 0.056218186 | AD28: Overstock | AE28: 180.58855 | AF28: Overstock | AG28: 161.73708 | AH28: Overstock | AI28: 139.9648 | AK28: Electronics | AL28: Simple Exponential Smoothing | AM28: 56754.254
A29: 45536 | B29: Outdoor & Sports | C29: 2112 | D29: TEST | E29: 1794 | F29: 0.15056818 | G29: 1633.2 | H29: 0.22670455 | I29: 1762.2852 | J29: 0.16558465 | L29: Total | M29: 98106.3 | O29: 126226.28 | Q29: 97314.993 | S29: 45536 | T29: Health & Beauty | U29: 1045 | V29: TEST | W29: 1107 | X29: 0.059330144 | Y29: 1108.5 | Z29: 0.06076555 | AA29: 1252.2933 | AB29: 0.19836676 | AD29: Total | AE29: 32390.603 | AG29: 20917.378 | AI29: 22383.558 | AK29: Electronics | AL29: Holt-Winters Seasonal Method | AM29: 39185.013
A30: 45566 | B30: Outdoor & Sports | C30: 1488 | D30: TEST | E30: 1917.7 | F30: 0.28877688 | G30: 1681.1 | H30: 0.12977151 | I30: 1883.3568 | J30: 0.26569677 | S30: 45566 | T30: Health & Beauty | U30: 1072 | V30: TEST | W30: 1050.7 | X30: 0.019869403 | Y30: 1090.7 | Z30: 0.01744403 | AA30: 1072.5611 | AB30: 0.00052339423 | AK30: Health & Beauty | AL30: MOVING AVG 3. MONTHS | AM30: 32390.603
A31: 45597 | B31: Outdoor & Sports | C31: 1567 | D31: TEST | E31: 1881.3 | F31: 0.20057435 | G31: 1661.8 | H31: 0.060497766 | I31: 1809.8572 | J31: 0.15498226 | S31: 45597 | T31: Health & Beauty | U31: 1010 | V31: TEST | W31: 1094.3 | X31: 0.083465347 | Y31: 1085.5 | Z31: 0.074752475 | AA31: 1076.3137 | AB31: 0.065657147 | AK31: Health & Beauty | AL31: Simple Exponential Smoothing | AM31: 20917.378
AK32: Health & Beauty | AL32: Holt-Winters Seasonal Method | AM32: 22383.558
A33: Mean Absolute Percentage Error | E33: MAPE | F33: 0.16091558 | H33: 0.12422296 | J33: 0.14694822 | S33: Mean Absolute Percentage Error | W33: MAPE | X33: 0.094064971 | Z33: 0.086236091 | AB33: 0.10727702 | AK33: Home & Kitchen | AL33: MOVING AVG 3. MONTHS | AM33: 49063.849
AK34: Home & Kitchen | AL34: Simple Exponential Smoothing | AM34: 63105.896
AK35: Home & Kitchen | AL35: Holt-Winters Seasonal Method | AM35: 72368.511
AK36: Office Supplies | AL36: MOVING AVG 3. MONTHS | AM36: 83309.305
E37: a | F37: 0.01 | W37: a | X37: 0.07 | AK37: Office Supplies | AL37: Simple Exponential Smoothing | AM37: 86281.092
A38: Month | B38: Category | C38: Actual | D38: SET | E38: MOVING AVG 3. MONTHS | F38: % error per month | G38: Simple Exponential Smoothing | H38: % error per month | I38: Holt-Winters Seasonal Method | J38: % error per month | S38: Month | T38: Category | U38: Actual | V38: SET | W38: MOVING AVG 3. MONTHS | X38: % error per month | Y38: Simple Exponential Smoothing | Z38: % error per month | AA38: Holt-Winters Seasonal Method | AB38: % error per month | AK38: Office Supplies | AL38: Holt-Winters Seasonal Method | AM38: 88690.39
A39: 44927 | B39: Home & Kitchen | C39: 945 | D39: TRAIN | G39: 945 | L39: Model | M39: MAPE | S39: 44927 | T39: Office Supplies | U39: 1536 | V39: TRAIN | Y39: 1536 | AD39: Model | AE39: MAPE | AK39: Outdoor & Sports | AL39: MOVING AVG 3. MONTHS | AM39: 98106.3
A40: 44958 | B40: Home & Kitchen | C40: 1183 | D40: TRAIN | G40: 945 | L40: Moving Averge (3 Month) | M40: 0.19659204 | S40: 44958 | T40: Office Supplies | U40: 1339 | V40: TRAIN | Y40: 1536 | AD40: Moving Averge (3 Month) | AE40: 0.17927731 | AK40: Outdoor & Sports | AL40: Simple Exponential Smoothing | AM40: 126226.28
A41: 44986 | B41: Home & Kitchen | C41: 1085 | D41: TRAIN | G41: 947.4 | L41: Simple Exponential Smoothing (a=0.3) | M41: 0.19669051 | S41: 44986 | T41: Office Supplies | U41: 1430 | V41: TRAIN | Y41: 1522.2 | AD41: Simple Exponential Smoothing (a=0.3) | AE41: 0.1589617 | AK41: Outdoor & Sports | AL41: Holt-Winters Seasonal Method | AM41: 97314.993
A42: 45017 | B42: Home & Kitchen | C42: 997 | D42: TRAIN | G42: 948.8 | L42: Simple Exponential Smoothing (a=0.2) | M42: 0.18700905 | S42: 45017 | T42: Office Supplies | U42: 1486 | V42: TRAIN | Y42: 1515.7 | AD42: Simple Exponential Smoothing (a=0.2) | AE42: 0.15197871
A43: 45047 | B43: Home & Kitchen | C43: 866 | D43: TRAIN | G43: 949.3 | L43: Simple Exponential Smoothing (a=0.4) | M43: 0.2065846 | S43: 45047 | T43: Office Supplies | U43: 1261 | V43: TRAIN | Y43: 1513.6 | AD43: Simple Exponential Smoothing (a=0.4) | AE43: 0.16456156
A44: 45078 | B44: Home & Kitchen | C44: 623 | D44: TRAIN | G44: 948.5 | L44: Simple Exponential Smoothing (a=0.15) | M44: 0.18229445 | S44: 45078 | T44: Office Supplies | U44: 1060 | V44: TRAIN | Y44: 1495.9 | AD44: Simple Exponential Smoothing (a=0.15) | AE44: 0.14823588
A45: 45108 | B45: Home & Kitchen | C45: 1014 | D45: TRAIN | G45: 945.2 | L45: Simple Exponential Smoothing (a=0.1) | M45: 0.17764339 | S45: 45108 | T45: Office Supplies | U45: 1301 | V45: TRAIN | Y45: 1465.4 | AD45: Simple Exponential Smoothing (a=0.1) | AE45: 0.1450948
A46: 45139 | B46: Home & Kitchen | C46: 964 | D46: TRAIN | G46: 945.9 | L46: Simple Exponential Smoothing (a=0.01) | M46: 0.16217634 | N46: Model | O46: MAPE | P46: Total Cost (6 months) | S46: 45139 | T46: Office Supplies | U46: 1101 | V46: TRAIN | Y46: 1453.9 | AD46: Simple Exponential Smoothing (a=0.07) | AE46: 0.14429349 | AF46: Model | AG46: MAPE | AH46: Total Cost (6 months)
A47: 45170 | B47: Home & Kitchen | C47: 1056 | D47: TRAIN | G47: 946.1 | N47: MOVING AVG 3. MONTHS | O47: 0.19659204 | P47: 49063.849 | S47: 45170 | T47: Office Supplies | U47: 1297 | V47: TRAIN | Y47: 1429.2 | AF47: MOVING AVG 3. MONTHS | AG47: 0.17927731 | AH47: 83309.305
A48: 45200 | B48: Home & Kitchen | C48: 884 | D48: TRAIN | G48: 947.2 | L48: Margin | M48: 112.5125 | N48: Simple Exponential Smoothing | O48: 0.16217634 | P48: 63105.896 | S48: 45200 | T48: Office Supplies | U48: 1477 | V48: TRAIN | Y48: 1419.9 | AD48: Margin | AE48: 111.35659 | AF48: Simple Exponential Smoothing | AG48: 0.14429349 | AH48: 86281.092
A49: 45231 | B49: Home & Kitchen | C49: 946 | D49: TRAIN | G49: 946.6 | L49: Holding rate | M49: 0.0167 | N49: Holt-Winters Seasonal Method | O49: 0.24810034 | P49: 72368.511 | S49: 45231 | T49: Office Supplies | U49: 1017 | V49: TRAIN | Y49: 1423.9 | AD49: Holding rate | AE49: 0.0167 | AF49: Holt-Winters Seasonal Method | AG49: 0.12898637 | AH49: 88690.39
A50: 45261 | B50: Home & Kitchen | C50: 1076 | D50: TRAIN | G50: 946.6 | L50: Unit Cost | M50: 132.9625 | S50: 45261 | T50: Office Supplies | U50: 1392 | V50: TRAIN | Y50: 1395.4 | AD50: Unit Cost | AE50: 131.58455
A51: 45292 | B51: Home & Kitchen | C51: 931 | D51: TRAIN | G51: 947.9 | S51: 45292 | T51: Office Supplies | U51: 1601 | V51: TRAIN | Y51: 1395.2
A52: 45323 | B52: Home & Kitchen | C52: 840 | D52: TRAIN | G52: 947.7 | L52: Type (Moving Average) | M52: Cost Impact | N52: Type (Simple Exponential Smoothing) | O52: Cost Impact | P52: Type (Holt-Winters Seasonal Method) | Q52: Cost Impact | S52: 45323 | T52: Office Supplies | U52: 1067 | V52: TRAIN | Y52: 1409.6 | AD52: Type (Moving Average) | AE52: Cost Impact | AF52: Type (Simple Exponential Smoothing) | AG52: Cost Impact | AH52: Type (Holt-Winters Seasonal Method) | AI52: Cost Impact
A53: 45352 | B53: Home & Kitchen | C53: 1021 | D53: TRAIN | G53: 946.6 | L53: Understock | M53: 9529.8088 | N53: Understock | O53: 14739.138 | P53: Understock | Q53: 18040.058 | S53: 45352 | T53: Office Supplies | U53: 1438 | V53: TRAIN | Y53: 1385.6 | AD53: Overstock | AE53: 291.5482 | AF53: Overstock | AG53: 335.06949 | AH53: Overstock | AI53: 97.31379
A54: 45383 | B54: Home & Kitchen | C54: 868 | D54: TRAIN | G54: 947.3 | L54: Overstock | M54: 339.06634 | N54: Overstock | O54: 196.06783 | P54: Overstock | Q54: 399.7446 | S54: 45383 | T54: Office Supplies | U54: 1374 | V54: TRAIN | Y54: 1389.3 | AD54: Understock | AE54: 36262.779 | AF54: Understock | AG54: 27419.296 | AH54: Understock | AI54: 23469.587
A55: 45413 | B55: Home & Kitchen | C55: 1094 | D55: TRAIN | G55: 946.5 | L55: Understock | M55: 36645.321 | N55: Understock | O55: 43722.358 | P55: Understock | Q55: 40921.745 | S55: 45413 | T55: Office Supplies | U55: 1269 | V55: TRAIN | Y55: 1388.2 | AD55: Understock | AE55: 45308.784 | AF55: Understock | AG55: 43497.333 | AH55: Understock | AI55: 63776.729
A56: 45444 | B56: Home & Kitchen | C56: 1079 | D56: TEST | E56: 994.3 | F56: 0.07849861 | G56: 948 | H56: 0.12140871 | I56: 918.66175 | J56: 0.14859894 | L56: Overstock | M56: 613.5169 | N56: Overstock | O56: 302.65057 | P56: Overstock | Q56: 670.68149 | S56: 45444 | T56: Office Supplies | U56: 1229 | V56: TEST | W56: 1360.3 | X56: 0.10683483 | Y56: 1379.9 | Z56: 0.12278275 | AA56: 1272.8257 | AB56: 0.035659632 | AD56: Overstock | AE56: 355.94194 | AF56: Overstock | AG56: 78.826818 | AH56: Overstock | AI56: 356.41665
A57: 45474 | B57: Home & Kitchen | C57: 861 | D57: TEST | E57: 1013.7 | F57: 0.17735192 | G57: 949.3 | H57: 0.10255517 | I57: 1041.0267 | J57: 0.20909027 | L57: Overstock | M57: 552.23182 | N57: Overstock | O57: 432.77033 | P57: Overstock | Q57: 642.75118 | S57: 45474 | T57: Office Supplies | U57: 1613 | V57: TEST | W57: 1290.7 | X57: 0.19981401 | Y57: 1369.3 | Z57: 0.15108493 | AA57: 1404.4046 | AB57: 0.12932137 | AD57: Overstock | AE57: 111.02369 | AF57: Understock | AG57: 14289.088 | AH57: Understock | AI57: 568.14825
A58: 45505 | B58: Home & Kitchen | C58: 1337 | D58: TEST | E58: 1011.3 | F58: 0.24360509 | G58: 948.4 | H58: 0.29065071 | I58: 973.29157 | J58: 0.27203323 | L58: Understock | M58: 1383.9037 | N58: Understock | O58: 3712.9125 | P58: Understock | Q58: 11693.532 | S58: 45505 | T58: Office Supplies | U58: 1773 | V58: TEST | W58: 1370.3 | X58: 0.22712916 | Y58: 1386.4 | Z58: 0.21804851 | AA58: 1206.1587 | AB58: 0.31970743 | AD58: Overstock | AE58: 979.22892 | AF58: Overstock | AG58: 661.47913 | AH58: Overstock | AI58: 422.19624
A59: 45536 | B59: Home & Kitchen | C59: 816 | D59: TEST | E59: 1092.3 | F59: 0.33860294 | G59: 952.3 | H59: 0.16703431 | I59: 1118.0443 | J59: 0.37015235 | L59: Total | M59: 49063.849 | O59: 63105.896 | Q59: 72368.511 | S59: 45536 | T59: Office Supplies | U59: 1378 | V59: TEST | W59: 1538.3 | X59: 0.11632801 | Y59: 1413.5 | Z59: 0.025761974 | AA59: 1538.5138 | AB59: 0.11648315 | AD59: Total | AE59: 83309.305 | AG59: 86281.092 | AI59: 88690.391
A60: 45566 | B60: Home & Kitchen | C60: 756 | D60: TEST | E60: 1004.7 | F60: 0.32896825 | G60: 950.9 | H60: 0.25780423 | I60: 1045.4658 | J60: 0.38289125 | S60: 45566 | T60: Office Supplies | U60: 1538 | V60: TEST | W60: 1588 | X60: 0.032509753 | Y60: 1411 | Z60: 0.082574772 | AA60: 1532.9504 | AB60: 0.0032832546
A61: 45597 | B61: Home & Kitchen | C61: 982 | D61: TEST | E61: 969.7 | F61: 0.012525458 | G61: 949 | H61: 0.033604888 | I61: 878.06904 | J61: 0.10583601 | S61: 45597 | T61: Office Supplies | U61: 1122 | V61: TEST | W61: 1563 | X61: 0.39304813 | Y61: 1419.9 | Z61: 0.26550802 | AA61: 1312.1379 | AB61: 0.16946338
A63: Mean Absolute Percentage Error | E63: MAPE | F63: 0.19659204 | H63: 0.16217634 | J63: 0.24810034 | S63: Mean Absolute Percentage Error | W63: MAPE | X63: 0.17927731 | Z63: 0.14429349 | AB63: 0.12898637
E66: a | F66: 0.2
A67: Month | B67: Category | C67: Actual | D67: SET | E67: MOVING AVG 3. MONTHS | F67: % error per month | G67: Simple Exponential Smoothing | H67: % error per month | I67: Holt-Winters Seasonal Method | J67: % error per month
A68: 44927 | B68: Electronics | C68: 893 | D68: TRAIN | G68: 893 | L68: Model | M68: MAPE
A69: 44958 | B69: Electronics | C69: 883 | D69: TRAIN | G69: 893 | L69: Moving Averge (3 Month) | M69: 0.18109327
A70: 44986 | B70: Electronics | C70: 1120 | D70: TRAIN | G70: 891 | L70: Simple Exponential Smoothing (a=0.3) | M70: 0.17312878
A71: 45017 | B71: Electronics | C71: 1077 | D71: TRAIN | G71: 936.8 | L71: Simple Exponential Smoothing (a=0.2) | M71: 0.17084664 | N71: Model | O71: MAPE | P71: Total Cost (6 months)
A72: 45047 | B72: Electronics | C72: 1105 | D72: TRAIN | G72: 964.8 | L72: Simple Exponential Smoothing (a=0.4) | M72: 0.17610002 | N72: MOVING AVG 3. MONTHS | O72: 0.18109327 | P72: 50700.988
A73: 45078 | B73: Electronics | C73: 1172 | D73: TRAIN | G73: 992.8 | L73: Simple Exponential Smoothing (a=0.15) | M73: 0.170978 | N73: Simple Exponential Smoothing | O73: 0.17084664 | P73: 56754.254
A74: 45108 | B74: Electronics | C74: 1044 | D74: TRAIN | G74: 1028.6 | L74: Simple Exponential Smoothing (a=0.1) | M74: 0.17331403 | N74: Holt-Winters Seasonal Method | O74: 0.15808821 | P74: 39185.013
A75: 45139 | B75: Electronics | C75: 1065 | D75: TRAIN | G75: 1031.7 | L75: Simple Exponential Smoothing (a=0.01) | M75: 0.20477151
A76: 45170 | B76: Electronics | C76: 984 | D76: TRAIN | G76: 1038.4 | U76: Row Labels | V76: Average of unit_cost | W76: Average of unit_price | X76: Margin | Y76: Stockout Cost June 2024
A77: 45200 | B77: Electronics | C77: 1097 | D77: TRAIN | G77: 1027.5 | L77: Margin | M77: 104.25286 | U77: Electronics | V77: 126.386 | W77: 230.63886 | X77: 104.25286
A78: 45231 | B78: Electronics | C78: 1167 | D78: TRAIN | G78: 1041.4 | L78: Holding rate | M78: 0.0167 | U78: Health & Beauty | V78: 152.93889 | W78: 275.7025 | X78: 122.76361
A79: 45261 | B79: Electronics | C79: 1125 | D79: TRAIN | G79: 1066.5 | L79: Unit Cost | M79: 126.386 | U79: Home & Kitchen | V79: 132.9625 | W79: 245.475 | X79: 112.5125
A80: 45292 | B80: Electronics | C80: 1185 | D80: TRAIN | G80: 1078.2 | U80: Office Supplies | V80: 131.58455 | W80: 242.94114 | X80: 111.35659
A81: 45323 | B81: Electronics | C81: 1055 | D81: TRAIN | G81: 1099.6 | L81: Type (Moving Average) | M81: Cost Impact | N81: Type (Simple Exponential Smoothing) | O81: Cost Impact | P81: Type (Holt-Winters Seasonal Method) | Q81: Cost Impact | U81: Outdoor & Sports | V81: 128.27623 | W81: 240.70868 | X81: 112.43245 | Y81: 19293.409
A82: 45352 | B82: Electronics | C82: 1261 | D82: TRAIN | G82: 1090.7 | L82: Understock | M82: 17201.721 | N82: Understock | O82: 17556.181 | P82: Understock | Q82: 16172.955 | U82: Grand Total | V82: 133.86235 | W82: 246.4991
A83: 45383 | B83: Electronics | C83: 865 | D83: TRAIN | G83: 1124.8 | L83: Understock | M83: 11332.286 | N83: Understock | O83: 7996.1941 | P83: Overstock | Q83: 15.316344
A84: 45413 | B84: Electronics | C84: 1147 | D84: TRAIN | G84: 1072.8 | L84: Understock | M84: 8621.7113 | N84: Understock | O84: 15262.618 | P84: Understock | Q84: 12051.714
A85: 45444 | B85: Electronics | C85: 1256 | D85: TEST | E85: 1091 | F85: 0.13136943 | G85: 1087.6 | H85: 0.13407643 | I85: 1100.868 | J85: 0.12351274 | L85: Overstock | M85: 560.7987 | N85: Overstock | O85: 392.36913 | P85: Overstock | Q85: 463.62673
A86: 45474 | B86: Electronics | C86: 1198 | D86: TEST | E86: 1089.3 | F86: 0.090734558 | G86: 1121.3 | H86: 0.064023372 | I86: 1205.2567 | J86: 0.0060573525 | L86: Understock | M86: 12228.86 | N86: Understock | O86: 14835.182 | P86: Understock | Q86: 9735.034
A87: 45505 | B87: Electronics | C87: 1283 | D87: TEST | E87: 1200.3 | F87: 0.064458301 | G87: 1136.6 | H87: 0.11410756 | I87: 1167.3992 | J87: 0.090101948 | L87: Overstock | M87: 755.61134 | N87: Overstock | O87: 711.7099 | P87: Overstock | Q87: 746.3674
A88: 45536 | B88: Electronics | C88: 980 | D88: TEST | E88: 1245.7 | F88: 0.27112245 | G88: 1165.9 | H88: 0.18969388 | I88: 1199.661 | J88: 0.22414392 | L88: Total | M88: 50700.988 | O88: 56754.254 | Q88: 39185.013
A89: 45566 | B89: Electronics | C89: 1271 | D89: TEST | E89: 1153.7 | F89: 0.092289536 | G89: 1128.7 | H89: 0.11195909 | I89: 1177.6209 | J89: 0.073468971
A90: 45597 | B90: Electronics | C90: 820 | D90: TEST | E90: 1178 | F90: 0.43658537 | G90: 1157.2 | H90: 0.41121951 | I90: 1173.6203 | J90: 0.4312443
A92: Mean Absolute Percentage Error | E92: MAPE | F92: 0.18109327 | H92: 0.17084664 | J92: 0.15808821
